{"playerA": 8467899, "playerB": 8475754, "date": "2025-09-13", "difficulty": "hard", "pathLength": 5, "solutions": [{"path_ids": [8467899, 8460542, 8470609, 8475754], "path_names": ["Martin Havlat", "Patrik Elias", "Steve Bernier", "Brock Nelson"], "length": 4, "toi_percentages": [20.4, 11.4, 4.1], "uniqueness_score": 8.4}, {"path_ids": [8467899, 8471233, 8475151, 8475754], "path_names": ["Martin Havlat", "Travis Zajac", "Kyle Palmieri", "Brock Nelson"], "length": 4, "toi_percentages": [13.8, 24.9, 21.0], "uniqueness_score": 16.7}, {"path_ids": [8467899, 8471233, 8470609, 8475754], "path_names": ["Martin Havlat", "Travis Zajac", "Steve Bernier", "Brock Nelson"], "length": 4, "toi_percentages": [13.8, 1.9, 4.1], "uniqueness_score": 2.7}, {"path_ids": [8467899, 8467351, 8470609, 8475754], "path_names": ["Martin Havlat", "Scott Gomez", "Steve Bernier", "Brock Nelson"], "length": 4, "toi_percentages": [9.5, 16.5, 4.1], "uniqueness_score": 6.4}, {"path_ids": [8467899, 8474053, 8468208, 8466251, 8475754], "path_names": ["Martin Havlat", "Logan Couture", "Joel Ward", "Jason Chimera", "Brock Nelson"], "length": 5, "toi_percentages": [20.7, 5.3, 24.7, 5.8], "uniqueness_score": 10.7}, {"path_ids": [8467899, 8474053, 8468208, 8471362, 8475754], "path_names": ["Martin Havlat", "Logan Couture", "Joel Ward", "Mikhail Grabovski", "Brock Nelson"], "length": 5, "toi_percentages": [20.7, 5.3, 3.4, 11.2], "uniqueness_score": 6.5}, {"path_ids": [8467899, 8460542, 8470920, 8473579, 8475754], "path_names": ["Martin Havlat", "Patrik Elias", "David Clarkson", "Nikolay Kulemin", "Brock Nelson"], "length": 5, "toi_percentages": [20.4, 16.4, 6.8, 11.3], "uniqueness_score": 10.2}, {"path_ids": [8467899, 8460542, 8470609, 8473579, 8475754], "path_names": ["Martin Havlat", "Patrik Elias", "Steve Bernier", "Nikolay Kulemin", "Brock Nelson"], "length": 5, "toi_percentages": [20.4, 11.4, 5.4, 11.3], "uniqueness_score": 8.6}, {"path_ids": [8467899, 8460542, 8470609, 8471362, 8475754], "path_names": ["Martin Havlat", "Patrik Elias", "Steve Bernier", "Mikhail Grabovski", "Brock Nelson"], "length": 5, "toi_percentages": [20.4, 11.4, 5.3, 11.2], "uniqueness_score": 8.5}, {"path_ids": [8467899, 8460542, 8470609, 8476386, 8475754], "path_names": ["Martin Havlat", "Patrik Elias", "Steve Bernier", "Shane Prince", "Brock Nelson"], "length": 5, "toi_percentages": [20.4, 11.4, 2.5, 33.0], "uniqueness_score": 13.5}, {"path_ids": [8467899, 8460542, 8472410, 8473504, 8475754], "path_names": ["Martin Havlat", "Patrik Elias", "Stephen Gionta", "Cal Clutterbuck", "Brock Nelson"], "length": 5, "toi_percentages": [20.4, 7.6, 4.3, 11.2], "uniqueness_score": 7.2}, {"path_ids": [8467899, 8471233, 8475151, 8477500, 8475754], "path_names": ["Martin Havlat", "Travis Zajac", "Kyle Palmieri", "Bo Horvat", "Brock Nelson"], "length": 5, "toi_percentages": [13.8, 24.9, 6.5, 4.4], "uniqueness_score": 8.8}, {"path_ids": [8467899, 8471233, 8475151, 8475314, 8475754], "path_names": ["Martin Havlat", "Travis Zajac", "Kyle Palmieri", "Anders Lee", "Brock Nelson"], "length": 5, "toi_percentages": [13.8, 24.9, 6.0, 26.7], "uniqueness_score": 14.6}, {"path_ids": [8467899, 8471233, 8475151, 8478115, 8475754], "path_names": ["Martin Havlat", "Travis Zajac", "Kyle Palmieri", "Pierre Engvall", "Brock Nelson"], "length": 5, "toi_percentages": [13.8, 24.9, 5.9, 18.0], "uniqueness_score": 12.3}, {"path_ids": [8467899, 8471233, 8475151, 8478445, 8475754], "path_names": ["Martin Havlat", "Travis Zajac", "Kyle Palmieri", "Mathew Barzal", "Brock Nelson"], "length": 5, "toi_percentages": [13.8, 24.9, 5.8, 13.6], "uniqueness_score": 11.1}, {"path_ids": [8467899, 8471233, 8475151, 8484958, 8475754], "path_names": ["Martin Havlat", "Travis Zajac", "Kyle Palmieri", "Maxim Tsyplakov", "Brock Nelson"], "length": 5, "toi_percentages": [13.8, 24.9, 3.6, 46.9], "uniqueness_score": 19.3}, {"path_ids": [8467899, 8471233, 8475151, 8481601, 8475754], "path_names": ["Martin Havlat", "Travis Zajac", "Kyle Palmieri", "Simon Holmstrom", "Brock Nelson"], "length": 5, "toi_percentages": [13.8, 24.9, 2.5, 13.3], "uniqueness_score": 10.1}, {"path_ids": [8467899, 8471233, 8475151, 8480789, 8475754], "path_names": ["Martin Havlat", "Travis Zajac", "Kyle Palmieri", "Oliver Wahlstrom", "Brock Nelson"], "length": 5, "toi_percentages": [13.8, 24.9, 1.5, 10.9], "uniqueness_score": 9.2}, {"path_ids": [8467899, 8471233, 8475151, 8477392, 8475754], "path_names": ["Martin Havlat", "Travis Zajac", "Kyle Palmieri", "Hudson Fasching", "Brock Nelson"], "length": 5, "toi_percentages": [13.8, 24.9, 0.9, 12.3], "uniqueness_score": 9.4}, {"path_ids": [8467899, 8471233, 8475151, 8479356, 8475754], "path_names": ["Martin Havlat", "Travis Zajac", "Kyle Palmieri", "Kieffer Bellows", "Brock Nelson"], "length": 5, "toi_percentages": [13.8, 24.9, 0.5, 18.5], "uniqueness_score": 11.0}, {"path_ids": [8467899, 8471233, 8475151, 8481016, 8475754], "path_names": ["Martin Havlat", "Travis Zajac", "Kyle Palmieri", "Ruslan Iskhakov", "Brock Nelson"], "length": 5, "toi_percentages": [13.8, 24.9, 0.0, 35.1], "uniqueness_score": 15.2}, {"path_ids": [8467899, 8471233, 8475151, 8480242, 8475754], "path_names": ["Martin Havlat", "Travis Zajac", "Kyle Palmieri", "Arnaud Durandeau", "Brock Nelson"], "length": 5, "toi_percentages": [13.8, 24.9, 0.0, 7.9], "uniqueness_score": 8.1}, {"path_ids": [8467899, 8471233, 8475791, 8474586, 8475754], "path_names": ["Martin Havlat", "Travis Zajac", "Taylor Hall", "Jordan Eberle", "Brock Nelson"], "length": 5, "toi_percentages": [13.8, 10.8, 13.5, 8.0], "uniqueness_score": 7.9}, {"path_ids": [8467899, 8471233, 8470920, 8473579, 8475754], "path_names": ["Martin Havlat", "Travis Zajac", "David Clarkson", "Nikolay Kulemin", "Brock Nelson"], "length": 5, "toi_percentages": [13.8, 3.4, 6.8, 11.3], "uniqueness_score": 5.1}, {"path_ids": [8467899, 8471233, 8476423, 8477500, 8475754], "path_names": ["Martin Havlat", "Travis Zajac", "Reid Boucher", "Bo Horvat", "Brock Nelson"], "length": 5, "toi_percentages": [13.8, 3.0, 11.3, 4.4], "uniqueness_score": 4.3}, {"path_ids": [8467899, 8471233, 8470609, 8473579, 8475754], "path_names": ["Martin Havlat", "Travis Zajac", "Steve Bernier", "Nikolay Kulemin", "Brock Nelson"], "length": 5, "toi_percentages": [13.8, 1.9, 5.4, 11.3], "uniqueness_score": 4.3}, {"path_ids": [8467899, 8471233, 8470609, 8471362, 8475754], "path_names": ["Martin Havlat", "Travis Zajac", "Steve Bernier", "Mikhail Grabovski", "Brock Nelson"], "length": 5, "toi_percentages": [13.8, 1.9, 5.3, 11.2], "uniqueness_score": 4.3}, {"path_ids": [8467899, 8471233, 8470609, 8476386, 8475754], "path_names": ["Martin Havlat", "Travis Zajac", "Steve Bernier", "Shane Prince", "Brock Nelson"], "length": 5, "toi_percentages": [13.8, 1.9, 2.5, 33.0], "uniqueness_score": 9.3}, {"path_ids": [8467899, 8466139, 8475172, 8473579, 8475754], "path_names": ["Martin Havlat", "Patrick Marleau", "Nazem Kadri", "Nikolay Kulemin", "Brock Nelson"], "length": 5, "toi_percentages": [13.8, 11.3, 2.8, 11.3], "uniqueness_score": 6.1}, {"path_ids": [8467899, 8466139, 8475172, 8473546, 8475754], "path_names": ["Martin Havlat", "Patrick Marleau", "Nazem Kadri", "Michael Grabner", "Brock Nelson"], "length": 5, "toi_percentages": [13.8, 11.3, 2.5, 5.1], "uniqueness_score": 4.4}, {"path_ids": [8467899, 8466139, 8468208, 8466251, 8475754], "path_names": ["Martin Havlat", "Patrick Marleau", "Joel Ward", "Jason Chimera", "Brock Nelson"], "length": 5, "toi_percentages": [13.8, 10.2, 24.7, 5.8], "uniqueness_score": 10.1}, {"path_ids": [8467899, 8466139, 8468208, 8471362, 8475754], "path_names": ["Martin Havlat", "Patrick Marleau", "Joel Ward", "Mikhail Grabovski", "Brock Nelson"], "length": 5, "toi_percentages": [13.8, 10.2, 3.4, 11.2], "uniqueness_score": 5.9}, {"path_ids": [8467899, 8466139, 8478483, 8475166, 8475754], "path_names": ["Martin Havlat", "Patrick Marleau", "Mitch Marner", "John Tavares", "Brock Nelson"], "length": 5, "toi_percentages": [13.8, 5.8, 33.2, 5.3], "uniqueness_score": 11.1}, {"path_ids": [8467899, 8466139, 8477953, 8478115, 8475754], "path_names": ["Martin Havlat", "Patrick Marleau", "Kasperi Kapanen", "Pierre Engvall", "Brock Nelson"], "length": 5, "toi_percentages": [13.8, 5.5, 3.1, 18.0], "uniqueness_score": 6.4}, {"path_ids": [8467899, 8466139, 8477939, 8475166, 8475754], "path_names": ["Martin Havlat", "Patrick Marleau", "William Nylander", "John Tavares", "Brock Nelson"], "length": 5, "toi_percentages": [13.8, 5.3, 40.4, 5.3], "uniqueness_score": 12.8}, {"path_ids": [8467899, 8466139, 8477939, 8478115, 8475754], "path_names": ["Martin Havlat", "Patrick Marleau", "William Nylander", "Pierre Engvall", "Brock Nelson"], "length": 5, "toi_percentages": [13.8, 5.3, 2.1, 18.0], "uniqueness_score": 6.1}, {"path_ids": [8467899, 8466139, 8479318, 8475166, 8475754], "path_names": ["Martin Havlat", "Patrick Marleau", "Auston Matthews", "John Tavares", "Brock Nelson"], "length": 5, "toi_percentages": [13.8, 5.3, 15.4, 5.3], "uniqueness_score": 6.3}, {"path_ids": [8467899, 8466139, 8473463, 8478445, 8475754], "path_names": ["Martin Havlat", "Patrick Marleau", "Leo Komarov", "Mathew Barzal", "Brock Nelson"], "length": 5, "toi_percentages": [13.8, 3.8, 6.2, 13.6], "uniqueness_score": 5.6}, {"path_ids": [8467899, 8466139, 8473463, 8478463, 8475754], "path_names": ["Martin Havlat", "Patrick Marleau", "Leo Komarov", "Anthony Beauvillier", "Brock Nelson"], "length": 5, "toi_percentages": [13.8, 3.8, 5.8, 37.7], "uniqueness_score": 11.9}, {"path_ids": [8467899, 8466139, 8473463, 8474709, 8475754], "path_names": ["Martin Havlat", "Patrick Marleau", "Leo Komarov", "Matt Martin", "Brock Nelson"], "length": 5, "toi_percentages": [13.8, 3.8, 5.6, 4.2], "uniqueness_score": 3.0}, {"path_ids": [8467899, 8466139, 8473463, 8474586, 8475754], "path_names": ["Martin Havlat", "Patrick Marleau", "Leo Komarov", "Jordan Eberle", "Brock Nelson"], "length": 5, "toi_percentages": [13.8, 3.8, 4.9, 8.0], "uniqueness_score": 3.8}, {"path_ids": [8467899, 8466139, 8473463, 8473546, 8475754], "path_names": ["Martin Havlat", "Patrick Marleau", "Leo Komarov", "Michael Grabner", "Brock Nelson"], "length": 5, "toi_percentages": [13.8, 3.8, 4.1, 5.1], "uniqueness_score": 2.8}, {"path_ids": [8467899, 8466139, 8473463, 8475832, 8475754], "path_names": ["Martin Havlat", "Patrick Marleau", "Leo Komarov", "Tom Kuhnhackl", "Brock Nelson"], "length": 5, "toi_percentages": [13.8, 3.8, 2.6, 6.5], "uniqueness_score": 2.8}, {"path_ids": [8467899, 8466139, 8473463, 8477936, 8475754], "path_names": ["Martin Havlat", "Patrick Marleau", "Leo Komarov", "Michael Dal Colle", "Brock Nelson"], "length": 5, "toi_percentages": [13.8, 3.8, 2.5, 31.0], "uniqueness_score": 9.2}, {"path_ids": [8467899, 8466139, 8473463, 8471362, 8475754], "path_names": ["Martin Havlat", "Patrick Marleau", "Leo Komarov", "Mikhail Grabovski", "Brock Nelson"], "length": 5, "toi_percentages": [13.8, 3.8, 2.2, 11.2], "uniqueness_score": 3.9}, {"path_ids": [8467899, 8466139, 8473463, 8477527, 8475754], "path_names": ["Martin Havlat", "Patrick Marleau", "Leo Komarov", "Ross Johnston", "Brock Nelson"], "length": 5, "toi_percentages": [13.8, 3.8, 1.6, 5.9], "uniqueness_score": 2.4}, {"path_ids": [8467899, 8466139, 8473463, 8479206, 8475754], "path_names": ["Martin Havlat", "Patrick Marleau", "Leo Komarov", "Tanner Fritz", "Brock Nelson"], "length": 5, "toi_percentages": [13.8, 3.8, 0.8, 52.9], "uniqueness_score": 14.6}, {"path_ids": [8467899, 8466139, 8473463, 8477959, 8475754], "path_names": ["Martin Havlat", "Patrick Marleau", "Leo Komarov", "Joshua Ho-Sang", "Brock Nelson"], "length": 5, "toi_percentages": [13.8, 3.8, 0.6, 51.0], "uniqueness_score": 14.0}, {"path_ids": [8467899, 8466138, 8478996, 8478115, 8475754], "path_names": ["Martin Havlat", "Joe Thornton", "Adam Brooks", "Pierre Engvall", "Brock Nelson"], "length": 5, "toi_percentages": [11.5, 0.5, 5.8, 18.0], "uniqueness_score": 5.2}, {"path_ids": [8467899, 8467351, 8470609, 8473579, 8475754], "path_names": ["Martin Havlat", "Scott Gomez", "Steve Bernier", "Nikolay Kulemin", "Brock Nelson"], "length": 5, "toi_percentages": [9.5, 16.5, 5.4, 11.3], "uniqueness_score": 7.0}, {"path_ids": [8467899, 8467351, 8470609, 8471362, 8475754], "path_names": ["Martin Havlat", "Scott Gomez", "Steve Bernier", "Mikhail Grabovski", "Brock Nelson"], "length": 5, "toi_percentages": [9.5, 16.5, 5.3, 11.2], "uniqueness_score": 7.0}, {"path_ids": [8467899, 8467351, 8470609, 8476386, 8475754], "path_names": ["Martin Havlat", "Scott Gomez", "Steve Bernier", "Shane Prince", "Brock Nelson"], "length": 5, "toi_percentages": [9.5, 16.5, 2.5, 33.0], "uniqueness_score": 12.0}, {"path_ids": [8467899, 8467351, 8468504, 8475166, 8475754], "path_names": ["Martin Havlat", "Scott Gomez", "Brad Boyes", "John Tavares", "Brock Nelson"], "length": 5, "toi_percentages": [9.5, 5.4, 19.6, 5.3], "uniqueness_score": 6.3}, {"path_ids": [8467899, 8467351, 8468504, 8473546, 8475754], "path_names": ["Martin Havlat", "Scott Gomez", "Brad Boyes", "Michael Grabner", "Brock Nelson"], "length": 5, "toi_percentages": [9.5, 5.4, 4.6, 5.1], "uniqueness_score": 2.3}, {"path_ids": [8467899, 8467351, 8470156, 8466251, 8475754], "path_names": ["Martin Havlat", "Scott Gomez", "Joey Crabb", "Jason Chimera", "Brock Nelson"], "length": 5, "toi_percentages": [9.5, 1.2, 8.8, 5.8], "uniqueness_score": 2.4}, {"path_ids": [8467899, 8469622, 8473544, 8478463, 8475754], "path_names": ["Martin Havlat", "Ryane Clowe", "Derick Brassard", "Anthony Beauvillier", "Brock Nelson"], "length": 5, "toi_percentages": [7.3, 6.4, 3.7, 37.7], "uniqueness_score": 10.3}, {"path_ids": [8467899, 8469622, 8473544, 8477936, 8475754], "path_names": ["Martin Havlat", "Ryane Clowe", "Derick Brassard", "Michael Dal Colle", "Brock Nelson"], "length": 5, "toi_percentages": [7.3, 6.4, 1.5, 31.0], "uniqueness_score": 7.9}, {"path_ids": [8467899, 8469622, 8473544, 8475832, 8475754], "path_names": ["Martin Havlat", "Ryane Clowe", "Derick Brassard", "Tom Kuhnhackl", "Brock Nelson"], "length": 5, "toi_percentages": [7.3, 6.4, 1.2, 6.5], "uniqueness_score": 1.4}, {"path_ids": [8467899, 8469622, 8472410, 8473504, 8475754], "path_names": ["Martin Havlat", "Ryane Clowe", "Stephen Gionta", "Cal Clutterbuck", "Brock Nelson"], "length": 5, "toi_percentages": [7.3, 4.8, 4.3, 11.2], "uniqueness_score": 3.1}, {"path_ids": [8467899, 8471311, 8476423, 8477500, 8475754], "path_names": ["Martin Havlat", "Tyler Kennedy", "Reid Boucher", "Bo Horvat", "Brock Nelson"], "length": 5, "toi_percentages": [6.6, 5.1, 11.3, 4.4], "uniqueness_score": 3.0}, {"path_ids": [8467899, 8471311, 8474024, 8471299, 8475754], "path_names": ["Martin Havlat", "Tyler Kennedy", "Jim O'Brien", "Peter Regin", "Brock Nelson"], "length": 5, "toi_percentages": [6.6, 1.2, 20.5, 8.2], "uniqueness_score": 5.4}, {"path_ids": [8467899, 8476442, 8474009, 8475832, 8475754], "path_names": ["Martin Havlat", "Matt Nieto", "Nick Bonino", "Tom Kuhnhackl", "Brock Nelson"], "length": 5, "toi_percentages": [4.2, 6.9, 1.3, 6.5], "uniqueness_score": 0.8}, {"path_ids": [8467899, 8476442, 8468208, 8466251, 8475754], "path_names": ["Martin Havlat", "Matt Nieto", "Joel Ward", "Jason Chimera", "Brock Nelson"], "length": 5, "toi_percentages": [4.2, 4.2, 24.7, 5.8], "uniqueness_score": 6.0}, {"path_ids": [8467899, 8476442, 8468208, 8471362, 8475754], "path_names": ["Martin Havlat", "Matt Nieto", "Joel Ward", "Mikhail Grabovski", "Brock Nelson"], "length": 5, "toi_percentages": [4.2, 4.2, 3.4, 11.2], "uniqueness_score": 1.8}, {"path_ids": [8467899, 8476442, 8479370, 8473449, 8475754], "path_names": ["Martin Havlat", "Matt Nieto", "Tyson Jost", "Kyle Okposo", "Brock Nelson"], "length": 5, "toi_percentages": [4.2, 2.9, 4.6, 5.8], "uniqueness_score": 0.4}, {"path_ids": [8467899, 8476442, 8483570, 8477527, 8475754], "path_names": ["Martin Havlat", "Matt Nieto", "Ben Meyers", "Ross Johnston", "Brock Nelson"], "length": 5, "toi_percentages": [4.2, 0.5, 6.2, 5.9], "uniqueness_score": 0.2}, {"path_ids": [8467899, 8471996, 8472410, 8473504, 8475754], "path_names": ["Martin Havlat", "Bracken Kearns", "Stephen Gionta", "Cal Clutterbuck", "Brock Nelson"], "length": 5, "toi_percentages": [1.5, 4.3, 4.3, 11.2], "uniqueness_score": 1.4}, {"path_ids": [8467899, 8474053, 8475169, 8466140, 8471217, 8475754], "path_names": ["Martin Havlat", "Logan Couture", "Evander Kane", "Olli Jokinen", "Andrew Ladd", "Brock Nelson"], "length": 6, "toi_percentages": [20.7, 10.0, 6.1, 6.2, 9.4], "uniqueness_score": 6.8}, {"path_ids": [8467899, 8474053, 8475169, 8471218, 8471217, 8475754], "path_names": ["Martin Havlat", "Logan Couture", "Evander Kane", "Blake Wheeler", "Andrew Ladd", "Brock Nelson"], "length": 6, "toi_percentages": [20.7, 10.0, 5.1, 15.7, 9.4], "uniqueness_score": 8.6}, {"path_ids": [8467899, 8474053, 8475169, 8469506, 8470153, 8475754], "path_names": ["Martin Havlat", "Logan Couture", "Evander Kane", "Jason Pominville", "Pierre-Marc Bouchard", "Brock Nelson"], "length": 6, "toi_percentages": [20.7, 10.0, 3.1, 0.9, 5.1], "uniqueness_score": 4.2}, {"path_ids": [8467899, 8474053, 8475169, 8473564, 8471217, 8475754], "path_names": ["Martin Havlat", "Logan Couture", "Evander Kane", "Michael Frolik", "Andrew Ladd", "Brock Nelson"], "length": 6, "toi_percentages": [20.7, 10.0, 2.8, 10.7, 9.4], "uniqueness_score": 7.1}, {"path_ids": [8467899, 8474053, 8475169, 8471682, 8470153, 8475754], "path_names": ["Martin Havlat", "Logan Couture", "Evander Kane", "Devin Setoguchi", "Pierre-Marc Bouchard", "Brock Nelson"], "length": 6, "toi_percentages": [20.7, 10.0, 2.3, 8.6, 5.1], "uniqueness_score": 5.6}, {"path_ids": [8467899, 8474053, 8475169, 8471682, 8471217, 8475754], "path_names": ["Martin Havlat", "Logan Couture", "Evander Kane", "Devin Setoguchi", "Andrew Ladd", "Brock Nelson"], "length": 6, "toi_percentages": [20.7, 10.0, 2.3, 5.4, 9.4], "uniqueness_score": 5.9}, {"path_ids": [8467899, 8474053, 8475169, 8479344, 8476458, 8475754], "path_names": ["Martin Havlat", "Logan Couture", "Evander Kane", "Jesse Puljujarvi", "Ryan Strome", "Brock Nelson"], "length": 6, "toi_percentages": [20.7, 10.0, 1.8, 6.1, 9.7], "uniqueness_score": 6.0}, {"path_ids": [8467899, 8474053, 8475169, 8475788, 8471217, 8475754], "path_names": ["Martin Havlat", "Logan Couture", "Evander Kane", "Alexander Burmistrov", "Andrew Ladd", "Brock Nelson"], "length": 6, "toi_percentages": [20.7, 10.0, 1.7, 6.8, 9.4], "uniqueness_score": 6.0}, {"path_ids": [8467899, 8474053, 8475169, 8467353, 8471217, 8475754], "path_names": ["Martin Havlat", "Logan Couture", "Evander Kane", "Nik Antropov", "Andrew Ladd", "Brock Nelson"], "length": 6, "toi_percentages": [20.7, 10.0, 1.6, 18.6, 9.4], "uniqueness_score": 8.5}, {"path_ids": [8467899, 8474053, 8475169, 8468704, 8471217, 8475754], "path_names": ["Martin Havlat", "Logan Couture", "Evander Kane", "Antti Miettinen", "Andrew Ladd", "Brock Nelson"], "length": 6, "toi_percentages": [20.7, 10.0, 1.2, 5.1, 9.4], "uniqueness_score": 5.6}, {"path_ids": [8467899, 8474053, 8475169, 8469581, 8471217, 8475754], "path_names": ["Martin Havlat", "Logan Couture", "Evander Kane", "Kyle Wellwood", "Andrew Ladd", "Brock Nelson"], "length": 6, "toi_percentages": [20.7, 10.0, 1.1, 4.4, 9.4], "uniqueness_score": 5.4}, {"path_ids": [8467899, 8474053, 8475169, 8470289, 8471217, 8475754], "path_names": ["Martin Havlat", "Logan Couture", "Evander Kane", "Jim Slater", "Andrew Ladd", "Brock Nelson"], "length": 6, "toi_percentages": [20.7, 10.0, 0.4, 4.0, 9.4], "uniqueness_score": 5.2}, {"path_ids": [8467899, 8474053, 8475169, 8471451, 8471217, 8475754], "path_names": ["Martin Havlat", "Logan Couture", "Evander Kane", "Aaron Gagnon", "Andrew Ladd", "Brock Nelson"], "length": 6, "toi_percentages": [20.7, 10.0, 0.1, 5.3, 9.4], "uniqueness_score": 5.4}, {"path_ids": [8467899, 8474053, 8468208, 8466251, 8476409, 8475754], "path_names": ["Martin Havlat", "Logan Couture", "Joel Ward", "Jason Chimera", "Alan Quine", "Brock Nelson"], "length": 6, "toi_percentages": [20.7, 5.3, 24.7, 8.3, 11.4], "uniqueness_score": 10.6}, {"path_ids": [8467899, 8474053, 8468208, 8466251, 8471217, 8475754], "path_names": ["Martin Havlat", "Logan Couture", "Joel Ward", "Jason Chimera", "Andrew Ladd", "Brock Nelson"], "length": 6, "toi_percentages": [20.7, 5.3, 24.7, 8.1, 9.4], "uniqueness_score": 10.1}, {"path_ids": [8467899, 8474053, 8468208, 8471362, 8476458, 8475754], "path_names": ["Martin Havlat", "Logan Couture", "Joel Ward", "Mikhail Grabovski", "Ryan Strome", "Brock Nelson"], "length": 6, "toi_percentages": [20.7, 5.3, 3.4, 17.4, 9.7], "uniqueness_score": 7.7}, {"path_ids": [8467899, 8474053, 8468208, 8471362, 8474573, 8475754], "path_names": ["Martin Havlat", "Logan Couture", "Joel Ward", "Mikhail Grabovski", "Josh Bailey", "Brock Nelson"], "length": 6, "toi_percentages": [20.7, 5.3, 3.4, 8.3, 28.3], "uniqueness_score": 9.7}, {"path_ids": [8467899, 8474053, 8479393, 8480890, 8471217, 8475754], "path_names": ["Martin Havlat", "Logan Couture", "Noah Gregor", "Jan Jenik", "Andrew Ladd", "Brock Nelson"], "length": 6, "toi_percentages": [20.7, 2.8, 0.4, 6.7, 9.4], "uniqueness_score": 4.2}, {"path_ids": [8467899, 8474053, 8478870, 8477935, 8476409, 8475754], "path_names": ["Martin Havlat", "Logan Couture", "Rudolfs Balcers", "Sam Bennett", "Alan Quine", "Brock Nelson"], "length": 6, "toi_percentages": [20.7, 2.1, 4.2, 0.5, 11.4], "uniqueness_score": 4.0}, {"path_ids": [8467899, 8474053, 8482667, 8475798, 8470153, 8475754], "path_names": ["Martin Havlat", "Logan Couture", "William Eklund", "Mikael Granlund", "Pierre-Marc Bouchard", "Brock Nelson"], "length": 6, "toi_percentages": [20.7, 0.9, 29.6, 0.5, 5.1], "uniqueness_score": 7.7}, {"path_ids": [8467899, 8474053, 8482133, 8475798, 8470153, 8475754], "path_names": ["Martin Havlat", "Logan Couture", "Thomas Bordeleau", "Mikael Granlund", "Pierre-Marc Bouchard", "Brock Nelson"], "length": 6, "toi_percentages": [20.7, 0.5, 15.0, 0.5, 5.1], "uniqueness_score": 4.6}, {"path_ids": [8467899, 8474053, 8475461, 8480031, 8476458, 8475754], "path_names": ["Martin Havlat", "Logan Couture", "Andrew Agozzino", "Maxime Comtois", "Ryan Strome", "Brock Nelson"], "length": 6, "toi_percentages": [20.7, 0.3, 4.1, 7.4, 9.7], "uniqueness_score": 4.7}, {"path_ids": [8467899, 8460542, 8474641, 8478873, 8476458, 8475754], "path_names": ["Martin Havlat", "Patrik Elias", "Adam Henrique", "Troy Terry", "Ryan Strome", "Brock Nelson"], "length": 6, "toi_percentages": [20.4, 28.5, 12.9, 21.1, 9.7], "uniqueness_score": 15.3}, {"path_ids": [8467899, 8460542, 8474641, 8481533, 8476458, 8475754], "path_names": ["Martin Havlat", "Patrik Elias", "Adam Henrique", "Trevor Zegras", "Ryan Strome", "Brock Nelson"], "length": 6, "toi_percentages": [20.4, 28.5, 6.4, 21.5, 9.7], "uniqueness_score": 14.0}, {"path_ids": [8467899, 8460542, 8474641, 8478366, 8476458, 8475754], "path_names": ["Martin Havlat", "Patrik Elias", "Adam Henrique", "Frank Vatrano", "Ryan Strome", "Brock Nelson"], "length": 6, "toi_percentages": [20.4, 28.5, 2.7, 25.3, 9.7], "uniqueness_score": 14.0}, {"path_ids": [8467899, 8460542, 8474641, 8482745, 8476458, 8475754], "path_names": ["Martin Havlat", "Patrik Elias", "Adam Henrique", "Mason McTavish", "Ryan Strome", "Brock Nelson"], "length": 6, "toi_percentages": [20.4, 28.5, 2.3, 19.7, 9.7], "uniqueness_score": 12.8}, {"path_ids": [8467899, 8460542, 8474641, 8480031, 8476458, 8475754], "path_names": ["Martin Havlat", "Patrik Elias", "Adam Henrique", "Maxime Comtois", "Ryan Strome", "Brock Nelson"], "length": 6, "toi_percentages": [20.4, 28.5, 2.2, 7.4, 9.7], "uniqueness_score": 10.1}, {"path_ids": [8467899, 8460542, 8474641, 8484153, 8476458, 8475754], "path_names": ["Martin Havlat", "Patrik Elias", "Adam Henrique", "Leo Carlsson", "Ryan Strome", "Brock Nelson"], "length": 6, "toi_percentages": [20.4, 28.5, 1.1, 12.8, 9.7], "uniqueness_score": 11.1}, {"path_ids": [8467899, 8460542, 8474641, 8481517, 8476458, 8475754], "path_names": ["Martin Havlat", "Patrik Elias", "Adam Henrique", "Brett Leason", "Ryan Strome", "Brock Nelson"], "length": 6, "toi_percentages": [20.4, 28.5, 0.7, 6.2, 9.7], "uniqueness_score": 9.6}, {"path_ids": [8467899, 8460542, 8470920, 8473579, 8476458, 8475754], "path_names": ["Martin Havlat", "Patrik Elias", "David Clarkson", "Nikolay Kulemin", "Ryan Strome", "Brock Nelson"], "length": 6, "toi_percentages": [20.4, 16.4, 6.8, 8.3, 9.7], "uniqueness_score": 8.8}, {"path_ids": [8467899, 8460542, 8470920, 8473579, 8474573, 8475754], "path_names": ["Martin Havlat", "Patrik Elias", "David Clarkson", "Nikolay Kulemin", "Josh Bailey", "Brock Nelson"], "length": 6, "toi_percentages": [20.4, 16.4, 6.8, 5.8, 28.3], "uniqueness_score": 12.1}, {"path_ids": [8467899, 8460542, 8470920, 8473579, 8476409, 8475754], "path_names": ["Martin Havlat", "Patrik Elias", "David Clarkson", "Nikolay Kulemin", "Alan Quine", "Brock Nelson"], "length": 6, "toi_percentages": [20.4, 16.4, 6.8, 1.7, 11.4], "uniqueness_score": 7.7}, {"path_ids": [8467899, 8460542, 8470609, 8473579, 8476458, 8475754], "path_names": ["Martin Havlat", "Patrik Elias", "Steve Bernier", "Nikolay Kulemin", "Ryan Strome", "Brock Nelson"], "length": 6, "toi_percentages": [20.4, 11.4, 5.4, 8.3, 9.7], "uniqueness_score": 7.4}, {"path_ids": [8467899, 8460542, 8470609, 8473579, 8474573, 8475754], "path_names": ["Martin Havlat", "Patrik Elias", "Steve Bernier", "Nikolay Kulemin", "Josh Bailey", "Brock Nelson"], "length": 6, "toi_percentages": [20.4, 11.4, 5.4, 5.8, 28.3], "uniqueness_score": 10.8}, {"path_ids": [8467899, 8460542, 8470609, 8473579, 8476409, 8475754], "path_names": ["Martin Havlat", "Patrik Elias", "Steve Bernier", "Nikolay Kulemin", "Alan Quine", "Brock Nelson"], "length": 6, "toi_percentages": [20.4, 11.4, 5.4, 1.7, 11.4], "uniqueness_score": 6.4}, {"path_ids": [8467899, 8460542, 8470609, 8471362, 8476458, 8475754], "path_names": ["Martin Havlat", "Patrik Elias", "Steve Bernier", "Mikhail Grabovski", "Ryan Strome", "Brock Nelson"], "length": 6, "toi_percentages": [20.4, 11.4, 5.3, 17.4, 9.7], "uniqueness_score": 9.3}, {"path_ids": [8467899, 8460542, 8470609, 8471362, 8474573, 8475754], "path_names": ["Martin Havlat", "Patrik Elias", "Steve Bernier", "Mikhail Grabovski", "Josh Bailey", "Brock Nelson"], "length": 6, "toi_percentages": [20.4, 11.4, 5.3, 8.3, 28.3], "uniqueness_score": 11.3}, {"path_ids": [8467899, 8460542, 8470609, 8476386, 8476458, 8475754], "path_names": ["Martin Havlat", "Patrik Elias", "Steve Bernier", "Shane Prince", "Ryan Strome", "Brock Nelson"], "length": 6, "toi_percentages": [20.4, 11.4, 2.5, 19.9, 9.7], "uniqueness_score": 9.2}, {"path_ids": [8467899, 8460542, 8470609, 8476386, 8471217, 8475754], "path_names": ["Martin Havlat", "Patrik Elias", "Steve Bernier", "Shane Prince", "Andrew Ladd", "Brock Nelson"], "length": 6, "toi_percentages": [20.4, 11.4, 2.5, 9.2, 9.4], "uniqueness_score": 6.9}, {"path_ids": [8467899, 8460542, 8470609, 8476386, 8476409, 8475754], "path_names": ["Martin Havlat", "Patrik Elias", "Steve Bernier", "Shane Prince", "Alan Quine", "Brock Nelson"], "length": 6, "toi_percentages": [20.4, 11.4, 2.5, 9.0, 11.4], "uniqueness_score": 7.3}, {"path_ids": [8467899, 8460542, 8470609, 8476386, 8474573, 8475754], "path_names": ["Martin Havlat", "Patrik Elias", "Steve Bernier", "Shane Prince", "Josh Bailey", "Brock Nelson"], "length": 6, "toi_percentages": [20.4, 11.4, 2.5, 6.4, 28.3], "uniqueness_score": 10.3}, {"path_ids": [8467899, 8460542, 8470609, 8460720, 8470644, 8475754], "path_names": ["Martin Havlat", "Patrik Elias", "Steve Bernier", "Eric Boulton", "Colin McDonald", "Brock Nelson"], "length": 6, "toi_percentages": [20.4, 11.4, 0.7, 7.6, 9.2], "uniqueness_score": 6.2}, {"path_ids": [8467899, 8460542, 8470609, 8460720, 8476458, 8475754], "path_names": ["Martin Havlat", "Patrik Elias", "Steve Bernier", "Eric Boulton", "Ryan Strome", "Brock Nelson"], "length": 6, "toi_percentages": [20.4, 11.4, 0.7, 6.1, 9.7], "uniqueness_score": 6.0}, {"path_ids": [8467899, 8460542, 8470609, 8460720, 8476765, 8475754], "path_names": ["Martin Havlat", "Patrik Elias", "Steve Bernier", "Eric Boulton", "Mike Halmo", "Brock Nelson"], "length": 6, "toi_percentages": [20.4, 11.4, 0.7, 3.8, 4.2], "uniqueness_score": 4.3}, {"path_ids": [8467899, 8460542, 8472410, 8473504, 8474573, 8475754], "path_names": ["Martin Havlat", "Patrik Elias", "Stephen Gionta", "Cal Clutterbuck", "Josh Bailey", "Brock Nelson"], "length": 6, "toi_percentages": [20.4, 7.6, 4.3, 4.7, 28.3], "uniqueness_score": 9.5}, {"path_ids": [8467899, 8460542, 8472410, 8473504, 8470153, 8475754], "path_names": ["Martin Havlat", "Patrik Elias", "Stephen Gionta", "Cal Clutterbuck", "Pierre-Marc Bouchard", "Brock Nelson"], "length": 6, "toi_percentages": [20.4, 7.6, 4.3, 2.2, 5.1], "uniqueness_score": 4.1}, {"path_ids": [8467899, 8460542, 8472410, 8473504, 8476409, 8475754], "path_names": ["Martin Havlat", "Patrik Elias", "Stephen Gionta", "Cal Clutterbuck", "Alan Quine", "Brock Nelson"], "length": 6, "toi_percentages": [20.4, 7.6, 4.3, 0.9, 11.4], "uniqueness_score": 5.2}, {"path_ids": [8467899, 8460542, 8472410, 8473504, 8476367, 8475754], "path_names": ["Martin Havlat", "Patrik Elias", "Stephen Gionta", "Cal Clutterbuck", "John Persson", "Brock Nelson"], "length": 6, "toi_percentages": [20.4, 7.6, 4.3, 0.5, 80.2], "uniqueness_score": 19.6}, {"path_ids": [8467899, 8460542, 8472410, 8477881, 8476409, 8475754], "path_names": ["Martin Havlat", "Patrik Elias", "Stephen Gionta", "Connor Jones", "Alan Quine", "Brock Nelson"], "length": 6, "toi_percentages": [20.4, 7.6, 0.8, 4.9, 11.4], "uniqueness_score": 5.3}, {"path_ids": [8467899, 8460542, 8472410, 8477881, 8474573, 8475754], "path_names": ["Martin Havlat", "Patrik Elias", "Stephen Gionta", "Connor Jones", "Josh Bailey", "Brock Nelson"], "length": 6, "toi_percentages": [20.4, 7.6, 0.8, 4.9, 28.3], "uniqueness_score": 8.8}, {"path_ids": [8467899, 8460542, 8469500, 8477415, 8476458, 8475754], "path_names": ["Martin Havlat", "Patrik Elias", "Michael Cammalleri", "Anton Slepyshev", "Ryan Strome", "Brock Nelson"], "length": 6, "toi_percentages": [20.4, 5.3, 1.4, 12.1, 9.7], "uniqueness_score": 6.1}, {"path_ids": [8467899, 8474739, 8467967, 8476419, 8474573, 8475754], "path_names": ["Martin Havlat", "Tommy Wingels", "Chris Kelly", "Jean-Gabriel Pageau", "Josh Bailey", "Brock Nelson"], "length": 6, "toi_percentages": [15.1, 4.1, 4.9, 5.8, 28.3], "uniqueness_score": 8.0}, {"path_ids": [8467899, 8474739, 8474096, 8464989, 8470153, 8475754], "path_names": ["Martin Havlat", "Tommy Wingels", "Nick Spaling", "Matt Cullen", "Pierre-Marc Bouchard", "Brock Nelson"], "length": 6, "toi_percentages": [15.1, 3.9, 5.7, 2.5, 5.1], "uniqueness_score": 2.6}, {"path_ids": [8467899, 8474739, 8474001, 8470289, 8471217, 8475754], "path_names": ["Martin Havlat", "Tommy Wingels", "TJ Galiardi", "Jim Slater", "Andrew Ladd", "Brock Nelson"], "length": 6, "toi_percentages": [15.1, 1.9, 11.9, 4.0, 9.4], "uniqueness_score": 4.7}, {"path_ids": [8467899, 8474739, 8478376, 8476419, 8474573, 8475754], "path_names": ["Martin Havlat", "Tommy Wingels", "Casey Bailey", "Jean-Gabriel Pageau", "Josh Bailey", "Brock Nelson"], "length": 6, "toi_percentages": [15.1, 0.1, 4.8, 5.8, 28.3], "uniqueness_score": 7.2}, {"path_ids": [8467899, 8471233, 8475151, 8476419, 8474573, 8475754], "path_names": ["Martin Havlat", "Travis Zajac", "Kyle Palmieri", "Jean-Gabriel Pageau", "Josh Bailey", "Brock Nelson"], "length": 6, "toi_percentages": [13.8, 24.9, 8.1, 5.8, 28.3], "uniqueness_score": 12.8}, {"path_ids": [8467899, 8471233, 8475151, 8475314, 8474573, 8475754], "path_names": ["Martin Havlat", "Travis Zajac", "Kyle Palmieri", "Anders Lee", "Josh Bailey", "Brock Nelson"], "length": 6, "toi_percentages": [13.8, 24.9, 6.0, 27.7, 28.3], "uniqueness_score": 17.0}, {"path_ids": [8467899, 8471233, 8475151, 8475314, 8476458, 8475754], "path_names": ["Martin Havlat", "Travis Zajac", "Kyle Palmieri", "Anders Lee", "Ryan Strome", "Brock Nelson"], "length": 6, "toi_percentages": [13.8, 24.9, 6.0, 7.3, 9.7], "uniqueness_score": 8.8}, {"path_ids": [8467899, 8471233, 8475151, 8475314, 8476409, 8475754], "path_names": ["Martin Havlat", "Travis Zajac", "Kyle Palmieri", "Anders Lee", "Alan Quine", "Brock Nelson"], "length": 6, "toi_percentages": [13.8, 24.9, 6.0, 0.8, 11.4], "uniqueness_score": 7.8}, {"path_ids": [8467899, 8471233, 8475151, 8478445, 8474573, 8475754], "path_names": ["Martin Havlat", "Travis Zajac", "Kyle Palmieri", "Mathew Barzal", "Josh Bailey", "Brock Nelson"], "length": 6, "toi_percentages": [13.8, 24.9, 5.8, 22.9, 28.3], "uniqueness_score": 15.9}, {"path_ids": [8467899, 8471233, 8475151, 8478445, 8471217, 8475754], "path_names": ["Martin Havlat", "Travis Zajac", "Kyle Palmieri", "Mathew Barzal", "Andrew Ladd", "Brock Nelson"], "length": 6, "toi_percentages": [13.8, 24.9, 5.8, 4.8, 9.4], "uniqueness_score": 8.1}, {"path_ids": [8467899, 8471233, 8475151, 8470610, 8470153, 8475754], "path_names": ["Martin Havlat", "Travis Zajac", "Kyle Palmieri", "Zach Parise", "Pierre-Marc Bouchard", "Brock Nelson"], "length": 6, "toi_percentages": [13.8, 24.9, 4.0, 0.4, 5.1], "uniqueness_score": 5.9}, {"path_ids": [8467899, 8471233, 8475151, 8480789, 8474573, 8475754], "path_names": ["Martin Havlat", "Travis Zajac", "Kyle Palmieri", "Oliver Wahlstrom", "Josh Bailey", "Brock Nelson"], "length": 6, "toi_percentages": [13.8, 24.9, 1.5, 13.2, 28.3], "uniqueness_score": 13.0}, {"path_ids": [8467899, 8471233, 8475151, 8479356, 8474573, 8475754], "path_names": ["Martin Havlat", "Travis Zajac", "Kyle Palmieri", "Kieffer Bellows", "Josh Bailey", "Brock Nelson"], "length": 6, "toi_percentages": [13.8, 24.9, 0.5, 14.3, 28.3], "uniqueness_score": 13.0}, {"path_ids": [8467899, 8471233, 8475151, 8479526, 8474573, 8475754], "path_names": ["Martin Havlat", "Travis Zajac", "Kyle Palmieri", "Otto Koivula", "Josh Bailey", "Brock Nelson"], "length": 6, "toi_percentages": [13.8, 24.9, 0.1, 22.7, 28.3], "uniqueness_score": 14.7}, {"path_ids": [8467899, 8471233, 8475151, 8480242, 8474573, 8475754], "path_names": ["Martin Havlat", "Travis Zajac", "Kyle Palmieri", "Arnaud Durandeau", "Josh Bailey", "Brock Nelson"], "length": 6, "toi_percentages": [13.8, 24.9, 0.0, 13.3, 28.3], "uniqueness_score": 12.7}, {"path_ids": [8467899, 8471233, 8475791, 8474586, 8471217, 8475754], "path_names": ["Martin Havlat", "Travis Zajac", "Taylor Hall", "Jordan Eberle", "Andrew Ladd", "Brock Nelson"], "length": 6, "toi_percentages": [13.8, 10.8, 13.5, 2.9, 9.4], "uniqueness_score": 6.4}, {"path_ids": [8467899, 8471233, 8475791, 8475745, 8470153, 8475754], "path_names": ["Martin Havlat", "Travis Zajac", "Taylor Hall", "Charlie Coyle", "Pierre-Marc Bouchard", "Brock Nelson"], "length": 6, "toi_percentages": [13.8, 10.8, 6.0, 0.3, 5.1], "uniqueness_score": 3.4}, {"path_ids": [8467899, 8471233, 8475791, 8476336, 8476458, 8475754], "path_names": ["Martin Havlat", "Travis Zajac", "Taylor Hall", "Iiro Pakarinen", "Ryan Strome", "Brock Nelson"], "length": 6, "toi_percentages": [13.8, 10.8, 0.8, 5.5, 9.7], "uniqueness_score": 4.3}, {"path_ids": [8467899, 8471233, 8469500, 8477415, 8476458, 8475754], "path_names": ["Martin Havlat", "Travis Zajac", "Michael Cammalleri", "Anton Slepyshev", "Ryan Strome", "Brock Nelson"], "length": 6, "toi_percentages": [13.8, 9.7, 1.4, 12.1, 9.7], "uniqueness_score": 5.6}, {"path_ids": [8467899, 8471233, 8474641, 8478873, 8476458, 8475754], "path_names": ["Martin Havlat", "Travis Zajac", "Adam Henrique", "Troy Terry", "Ryan Strome", "Brock Nelson"], "length": 6, "toi_percentages": [13.8, 6.7, 12.9, 21.1, 9.7], "uniqueness_score": 9.3}, {"path_ids": [8467899, 8471233, 8474641, 8481533, 8476458, 8475754], "path_names": ["Martin Havlat", "Travis Zajac", "Adam Henrique", "Trevor Zegras", "Ryan Strome", "Brock Nelson"], "length": 6, "toi_percentages": [13.8, 6.7, 6.4, 21.5, 9.7], "uniqueness_score": 8.0}, {"path_ids": [8467899, 8471233, 8474641, 8478366, 8476458, 8475754], "path_names": ["Martin Havlat", "Travis Zajac", "Adam Henrique", "Frank Vatrano", "Ryan Strome", "Brock Nelson"], "length": 6, "toi_percentages": [13.8, 6.7, 2.7, 25.3, 9.7], "uniqueness_score": 8.0}, {"path_ids": [8467899, 8471233, 8474641, 8482745, 8476458, 8475754], "path_names": ["Martin Havlat", "Travis Zajac", "Adam Henrique", "Mason McTavish", "Ryan Strome", "Brock Nelson"], "length": 6, "toi_percentages": [13.8, 6.7, 2.3, 19.7, 9.7], "uniqueness_score": 6.8}, {"path_ids": [8467899, 8471233, 8474641, 8480031, 8476458, 8475754], "path_names": ["Martin Havlat", "Travis Zajac", "Adam Henrique", "Maxime Comtois", "Ryan Strome", "Brock Nelson"], "length": 6, "toi_percentages": [13.8, 6.7, 2.2, 7.4, 9.7], "uniqueness_score": 4.2}, {"path_ids": [8467899, 8471233, 8474641, 8484153, 8476458, 8475754], "path_names": ["Martin Havlat", "Travis Zajac", "Adam Henrique", "Leo Carlsson", "Ryan Strome", "Brock Nelson"], "length": 6, "toi_percentages": [13.8, 6.7, 1.1, 12.8, 9.7], "uniqueness_score": 5.1}, {"path_ids": [8467899, 8471233, 8474641, 8481517, 8476458, 8475754], "path_names": ["Martin Havlat", "Travis Zajac", "Adam Henrique", "Brett Leason", "Ryan Strome", "Brock Nelson"], "length": 6, "toi_percentages": [13.8, 6.7, 0.7, 6.2, 9.7], "uniqueness_score": 3.6}, {"path_ids": [8467899, 8471233, 8470920, 8473579, 8476458, 8475754], "path_names": ["Martin Havlat", "Travis Zajac", "David Clarkson", "Nikolay Kulemin", "Ryan Strome", "Brock Nelson"], "length": 6, "toi_percentages": [13.8, 3.4, 6.8, 8.3, 9.7], "uniqueness_score": 4.6}, {"path_ids": [8467899, 8471233, 8470920, 8473579, 8474573, 8475754], "path_names": ["Martin Havlat", "Travis Zajac", "David Clarkson", "Nikolay Kulemin", "Josh Bailey", "Brock Nelson"], "length": 6, "toi_percentages": [13.8, 3.4, 6.8, 5.8, 28.3], "uniqueness_score": 8.0}, {"path_ids": [8467899, 8471233, 8470920, 8473579, 8476409, 8475754], "path_names": ["Martin Havlat", "Travis Zajac", "David Clarkson", "Nikolay Kulemin", "Alan Quine", "Brock Nelson"], "length": 6, "toi_percentages": [13.8, 3.4, 6.8, 1.7, 11.4], "uniqueness_score": 3.6}, {"path_ids": [8467899, 8471233, 8481068, 8478211, 8476458, 8475754], "path_names": ["Martin Havlat", "Travis Zajac", "Yegor Sharangovich", "Dryden Hunt", "Ryan Strome", "Brock Nelson"], "length": 6, "toi_percentages": [13.8, 2.4, 2.0, 13.8, 9.7], "uniqueness_score": 4.6}, {"path_ids": [8467899, 8471233, 8470609, 8473579, 8476458, 8475754], "path_names": ["Martin Havlat", "Travis Zajac", "Steve Bernier", "Nikolay Kulemin", "Ryan Strome", "Brock Nelson"], "length": 6, "toi_percentages": [13.8, 1.9, 5.4, 8.3, 9.7], "uniqueness_score": 4.0}, {"path_ids": [8467899, 8471233, 8470609, 8473579, 8474573, 8475754], "path_names": ["Martin Havlat", "Travis Zajac", "Steve Bernier", "Nikolay Kulemin", "Josh Bailey", "Brock Nelson"], "length": 6, "toi_percentages": [13.8, 1.9, 5.4, 5.8, 28.3], "uniqueness_score": 7.4}, {"path_ids": [8467899, 8471233, 8470609, 8473579, 8476409, 8475754], "path_names": ["Martin Havlat", "Travis Zajac", "Steve Bernier", "Nikolay Kulemin", "Alan Quine", "Brock Nelson"], "length": 6, "toi_percentages": [13.8, 1.9, 5.4, 1.7, 11.4], "uniqueness_score": 3.0}, {"path_ids": [8467899, 8471233, 8470609, 8471362, 8476458, 8475754], "path_names": ["Martin Havlat", "Travis Zajac", "Steve Bernier", "Mikhail Grabovski", "Ryan Strome", "Brock Nelson"], "length": 6, "toi_percentages": [13.8, 1.9, 5.3, 17.4, 9.7], "uniqueness_score": 5.9}, {"path_ids": [8467899, 8471233, 8470609, 8471362, 8474573, 8475754], "path_names": ["Martin Havlat", "Travis Zajac", "Steve Bernier", "Mikhail Grabovski", "Josh Bailey", "Brock Nelson"], "length": 6, "toi_percentages": [13.8, 1.9, 5.3, 8.3, 28.3], "uniqueness_score": 7.9}, {"path_ids": [8467899, 8471233, 8470609, 8476386, 8476458, 8475754], "path_names": ["Martin Havlat", "Travis Zajac", "Steve Bernier", "Shane Prince", "Ryan Strome", "Brock Nelson"], "length": 6, "toi_percentages": [13.8, 1.9, 2.5, 19.9, 9.7], "uniqueness_score": 5.9}, {"path_ids": [8467899, 8471233, 8470609, 8476386, 8471217, 8475754], "path_names": ["Martin Havlat", "Travis Zajac", "Steve Bernier", "Shane Prince", "Andrew Ladd", "Brock Nelson"], "length": 6, "toi_percentages": [13.8, 1.9, 2.5, 9.2, 9.4], "uniqueness_score": 3.5}, {"path_ids": [8467899, 8471233, 8470609, 8476386, 8476409, 8475754], "path_names": ["Martin Havlat", "Travis Zajac", "Steve Bernier", "Shane Prince", "Alan Quine", "Brock Nelson"], "length": 6, "toi_percentages": [13.8, 1.9, 2.5, 9.0, 11.4], "uniqueness_score": 3.9}, {"path_ids": [8467899, 8471233, 8470609, 8476386, 8474573, 8475754], "path_names": ["Martin Havlat", "Travis Zajac", "Steve Bernier", "Shane Prince", "Josh Bailey", "Brock Nelson"], "length": 6, "toi_percentages": [13.8, 1.9, 2.5, 6.4, 28.3], "uniqueness_score": 6.9}, {"path_ids": [8467899, 8471233, 8470609, 8460720, 8470644, 8475754], "path_names": ["Martin Havlat", "Travis Zajac", "Steve Bernier", "Eric Boulton", "Colin McDonald", "Brock Nelson"], "length": 6, "toi_percentages": [13.8, 1.9, 0.7, 7.6, 9.2], "uniqueness_score": 2.8}, {"path_ids": [8467899, 8471233, 8470609, 8460720, 8476458, 8475754], "path_names": ["Martin Havlat", "Travis Zajac", "Steve Bernier", "Eric Boulton", "Ryan Strome", "Brock Nelson"], "length": 6, "toi_percentages": [13.8, 1.9, 0.7, 6.1, 9.7], "uniqueness_score": 2.6}, {"path_ids": [8467899, 8471233, 8470609, 8460720, 8476765, 8475754], "path_names": ["Martin Havlat", "Travis Zajac", "Steve Bernier", "Eric Boulton", "Mike Halmo", "Brock Nelson"], "length": 6, "toi_percentages": [13.8, 1.9, 0.7, 3.8, 4.2], "uniqueness_score": 0.9}, {"path_ids": [8467899, 8471233, 8479315, 8476278, 8476458, 8475754], "path_names": ["Martin Havlat", "Travis Zajac", "Joey Anderson", "Colin Blackwell", "Ryan Strome", "Brock Nelson"], "length": 6, "toi_percentages": [13.8, 1.8, 13.8, 8.0, 9.7], "uniqueness_score": 5.7}, {"path_ids": [8467899, 8471233, 8479315, 8476915, 8476458, 8475754], "path_names": ["Martin Havlat", "Travis Zajac", "Joey Anderson", "Jujhar Khaira", "Ryan Strome", "Brock Nelson"], "length": 6, "toi_percentages": [13.8, 1.8, 11.4, 7.8, 9.7], "uniqueness_score": 5.2}, {"path_ids": [8467899, 8471233, 8473482, 8470289, 8471217, 8475754], "path_names": ["Martin Havlat", "Travis Zajac", "Jiri Tlusty", "Jim Slater", "Andrew Ladd", "Brock Nelson"], "length": 6, "toi_percentages": [13.8, 1.6, 4.3, 4.0, 9.4], "uniqueness_score": 2.8}, {"path_ids": [8467899, 8471233, 8473646, 8470803, 8470153, 8475754], "path_names": ["Martin Havlat", "Travis Zajac", "Ryan Carter", "Kyle Brodziak", "Pierre-Marc Bouchard", "Brock Nelson"], "length": 6, "toi_percentages": [13.8, 1.2, 9.7, 3.8, 5.1], "uniqueness_score": 2.9}, {"path_ids": [8467899, 8471233, 8473646, 8475745, 8470153, 8475754], "path_names": ["Martin Havlat", "Travis Zajac", "Ryan Carter", "Charlie Coyle", "Pierre-Marc Bouchard", "Brock Nelson"], "length": 6, "toi_percentages": [13.8, 1.2, 7.2, 0.3, 5.1], "uniqueness_score": 1.6}, {"path_ids": [8467899, 8471233, 8467412, 8475788, 8471217, 8475754], "path_names": ["Martin Havlat", "Travis Zajac", "Alexei Ponikarovsky", "Alexander Burmistrov", "Andrew Ladd", "Brock Nelson"], "length": 6, "toi_percentages": [13.8, 1.0, 17.4, 6.8, 9.4], "uniqueness_score": 6.0}, {"path_ids": [8467899, 8471233, 8467412, 8469581, 8471217, 8475754], "path_names": ["Martin Havlat", "Travis Zajac", "Alexei Ponikarovsky", "Kyle Wellwood", "Andrew Ladd", "Brock Nelson"], "length": 6, "toi_percentages": [13.8, 1.0, 13.7, 4.4, 9.4], "uniqueness_score": 4.7}, {"path_ids": [8467899, 8471233, 8467412, 8467353, 8471217, 8475754], "path_names": ["Martin Havlat", "Travis Zajac", "Alexei Ponikarovsky", "Nik Antropov", "Andrew Ladd", "Brock Nelson"], "length": 6, "toi_percentages": [13.8, 1.0, 8.5, 18.6, 9.4], "uniqueness_score": 6.6}, {"path_ids": [8467899, 8466139, 8475172, 8473579, 8476458, 8475754], "path_names": ["Martin Havlat", "Patrick Marleau", "Nazem Kadri", "Nikolay Kulemin", "Ryan Strome", "Brock Nelson"], "length": 6, "toi_percentages": [13.8, 11.3, 2.8, 8.3, 9.7], "uniqueness_score": 5.5}, {"path_ids": [8467899, 8466139, 8475172, 8473579, 8474573, 8475754], "path_names": ["Martin Havlat", "Patrick Marleau", "Nazem Kadri", "Nikolay Kulemin", "Josh Bailey", "Brock Nelson"], "length": 6, "toi_percentages": [13.8, 11.3, 2.8, 5.8, 28.3], "uniqueness_score": 8.8}, {"path_ids": [8467899, 8466139, 8475172, 8473579, 8476409, 8475754], "path_names": ["Martin Havlat", "Patrick Marleau", "Nazem Kadri", "Nikolay Kulemin", "Alan Quine", "Brock Nelson"], "length": 6, "toi_percentages": [13.8, 11.3, 2.8, 1.7, 11.4], "uniqueness_score": 4.4}, {"path_ids": [8467899, 8466139, 8475172, 8473546, 8474573, 8475754], "path_names": ["Martin Havlat", "Patrick Marleau", "Nazem Kadri", "Michael Grabner", "Josh Bailey", "Brock Nelson"], "length": 6, "toi_percentages": [13.8, 11.3, 2.5, 4.3, 28.3], "uniqueness_score": 8.5}, {"path_ids": [8467899, 8466139, 8475172, 8473546, 8470644, 8475754], "path_names": ["Martin Havlat", "Patrick Marleau", "Nazem Kadri", "Michael Grabner", "Colin McDonald", "Brock Nelson"], "length": 6, "toi_percentages": [13.8, 11.3, 2.5, 4.2, 9.2], "uniqueness_score": 4.4}, {"path_ids": [8467899, 8466139, 8468208, 8466251, 8476409, 8475754], "path_names": ["Martin Havlat", "Patrick Marleau", "Joel Ward", "Jason Chimera", "Alan Quine", "Brock Nelson"], "length": 6, "toi_percentages": [13.8, 10.2, 24.7, 8.3, 11.4], "uniqueness_score": 10.2}, {"path_ids": [8467899, 8466139, 8468208, 8466251, 8471217, 8475754], "path_names": ["Martin Havlat", "Patrick Marleau", "Joel Ward", "Jason Chimera", "Andrew Ladd", "Brock Nelson"], "length": 6, "toi_percentages": [13.8, 10.2, 24.7, 8.1, 9.4], "uniqueness_score": 9.7}, {"path_ids": [8467899, 8466139, 8468208, 8471362, 8476458, 8475754], "path_names": ["Martin Havlat", "Patrick Marleau", "Joel Ward", "Mikhail Grabovski", "Ryan Strome", "Brock Nelson"], "length": 6, "toi_percentages": [13.8, 10.2, 3.4, 17.4, 9.7], "uniqueness_score": 7.3}, {"path_ids": [8467899, 8466139, 8468208, 8471362, 8474573, 8475754], "path_names": ["Martin Havlat", "Patrick Marleau", "Joel Ward", "Mikhail Grabovski", "Josh Bailey", "Brock Nelson"], "length": 6, "toi_percentages": [13.8, 10.2, 3.4, 8.3, 28.3], "uniqueness_score": 9.3}, {"path_ids": [8467899, 8466139, 8478483, 8475166, 8474573, 8475754], "path_names": ["Martin Havlat", "Patrick Marleau", "Mitch Marner", "John Tavares", "Josh Bailey", "Brock Nelson"], "length": 6, "toi_percentages": [13.8, 5.8, 33.2, 18.2, 28.3], "uniqueness_score": 16.7}, {"path_ids": [8467899, 8466139, 8478483, 8475166, 8476458, 8475754], "path_names": ["Martin Havlat", "Patrick Marleau", "Mitch Marner", "John Tavares", "Ryan Strome", "Brock Nelson"], "length": 6, "toi_percentages": [13.8, 5.8, 33.2, 5.9, 9.7], "uniqueness_score": 10.2}, {"path_ids": [8467899, 8466139, 8478483, 8475166, 8471217, 8475754], "path_names": ["Martin Havlat", "Patrick Marleau", "Mitch Marner", "John Tavares", "Andrew Ladd", "Brock Nelson"], "length": 6, "toi_percentages": [13.8, 5.8, 33.2, 2.0, 9.4], "uniqueness_score": 9.3}, {"path_ids": [8467899, 8466139, 8478483, 8475166, 8476409, 8475754], "path_names": ["Martin Havlat", "Patrick Marleau", "Mitch Marner", "John Tavares", "Alan Quine", "Brock Nelson"], "length": 6, "toi_percentages": [13.8, 5.8, 33.2, 0.7, 11.4], "uniqueness_score": 9.5}, {"path_ids": [8467899, 8466139, 8478483, 8475166, 8470644, 8475754], "path_names": ["Martin Havlat", "Patrick Marleau", "Mitch Marner", "John Tavares", "Colin McDonald", "Brock Nelson"], "length": 6, "toi_percentages": [13.8, 5.8, 33.2, 0.4, 9.2], "uniqueness_score": 8.9}, {"path_ids": [8467899, 8466139, 8478483, 8475166, 8470153, 8475754], "path_names": ["Martin Havlat", "Patrick Marleau", "Mitch Marner", "John Tavares", "Pierre-Marc Bouchard", "Brock Nelson"], "length": 6, "toi_percentages": [13.8, 5.8, 33.2, 0.3, 5.1], "uniqueness_score": 8.0}, {"path_ids": [8467899, 8466139, 8477953, 8477402, 8476458, 8475754], "path_names": ["Martin Havlat", "Patrick Marleau", "Kasperi Kapanen", "Pavel Buchnevich", "Ryan Strome", "Brock Nelson"], "length": 6, "toi_percentages": [13.8, 5.5, 4.9, 4.4, 9.7], "uniqueness_score": 3.9}, {"path_ids": [8467899, 8466139, 8477939, 8475166, 8474573, 8475754], "path_names": ["Martin Havlat", "Patrick Marleau", "William Nylander", "John Tavares", "Josh Bailey", "Brock Nelson"], "length": 6, "toi_percentages": [13.8, 5.3, 40.4, 18.2, 28.3], "uniqueness_score": 18.1}, {"path_ids": [8467899, 8466139, 8477939, 8475166, 8476458, 8475754], "path_names": ["Martin Havlat", "Patrick Marleau", "William Nylander", "John Tavares", "Ryan Strome", "Brock Nelson"], "length": 6, "toi_percentages": [13.8, 5.3, 40.4, 5.9, 9.7], "uniqueness_score": 11.6}, {"path_ids": [8467899, 8466139, 8477939, 8475166, 8471217, 8475754], "path_names": ["Martin Havlat", "Patrick Marleau", "William Nylander", "John Tavares", "Andrew Ladd", "Brock Nelson"], "length": 6, "toi_percentages": [13.8, 5.3, 40.4, 2.0, 9.4], "uniqueness_score": 10.7}, {"path_ids": [8467899, 8466139, 8477939, 8475166, 8476409, 8475754], "path_names": ["Martin Havlat", "Patrick Marleau", "William Nylander", "John Tavares", "Alan Quine", "Brock Nelson"], "length": 6, "toi_percentages": [13.8, 5.3, 40.4, 0.7, 11.4], "uniqueness_score": 10.9}, {"path_ids": [8467899, 8466139, 8477939, 8475166, 8470644, 8475754], "path_names": ["Martin Havlat", "Patrick Marleau", "William Nylander", "John Tavares", "Colin McDonald", "Brock Nelson"], "length": 6, "toi_percentages": [13.8, 5.3, 40.4, 0.4, 9.2], "uniqueness_score": 10.3}, {"path_ids": [8467899, 8466139, 8477939, 8475166, 8470153, 8475754], "path_names": ["Martin Havlat", "Patrick Marleau", "William Nylander", "John Tavares", "Pierre-Marc Bouchard", "Brock Nelson"], "length": 6, "toi_percentages": [13.8, 5.3, 40.4, 0.3, 5.1], "uniqueness_score": 9.5}, {"path_ids": [8467899, 8466139, 8479318, 8475166, 8474573, 8475754], "path_names": ["Martin Havlat", "Patrick Marleau", "Auston Matthews", "John Tavares", "Josh Bailey", "Brock Nelson"], "length": 6, "toi_percentages": [13.8, 5.3, 15.4, 18.2, 28.3], "uniqueness_score": 12.8}, {"path_ids": [8467899, 8466139, 8479318, 8475166, 8476458, 8475754], "path_names": ["Martin Havlat", "Patrick Marleau", "Auston Matthews", "John Tavares", "Ryan Strome", "Brock Nelson"], "length": 6, "toi_percentages": [13.8, 5.3, 15.4, 5.9, 9.7], "uniqueness_score": 6.3}, {"path_ids": [8467899, 8466139, 8479318, 8475166, 8471217, 8475754], "path_names": ["Martin Havlat", "Patrick Marleau", "Auston Matthews", "John Tavares", "Andrew Ladd", "Brock Nelson"], "length": 6, "toi_percentages": [13.8, 5.3, 15.4, 2.0, 9.4], "uniqueness_score": 5.5}, {"path_ids": [8467899, 8466139, 8479318, 8475166, 8476409, 8475754], "path_names": ["Martin Havlat", "Patrick Marleau", "Auston Matthews", "John Tavares", "Alan Quine", "Brock Nelson"], "length": 6, "toi_percentages": [13.8, 5.3, 15.4, 0.7, 11.4], "uniqueness_score": 5.6}, {"path_ids": [8467899, 8466139, 8479318, 8475166, 8470644, 8475754], "path_names": ["Martin Havlat", "Patrick Marleau", "Auston Matthews", "John Tavares", "Colin McDonald", "Brock Nelson"], "length": 6, "toi_percentages": [13.8, 5.3, 15.4, 0.4, 9.2], "uniqueness_score": 5.1}, {"path_ids": [8467899, 8466139, 8479318, 8475166, 8470153, 8475754], "path_names": ["Martin Havlat", "Patrick Marleau", "Auston Matthews", "John Tavares", "Pierre-Marc Bouchard", "Brock Nelson"], "length": 6, "toi_percentages": [13.8, 5.3, 15.4, 0.3, 5.1], "uniqueness_score": 4.2}, {"path_ids": [8467899, 8466139, 8477015, 8476419, 8474573, 8475754], "path_names": ["Martin Havlat", "Patrick Marleau", "Connor Brown", "Jean-Gabriel Pageau", "Josh Bailey", "Brock Nelson"], "length": 6, "toi_percentages": [13.8, 4.1, 6.1, 5.8, 28.3], "uniqueness_score": 8.0}, {"path_ids": [8467899, 8466139, 8473463, 8478445, 8474573, 8475754], "path_names": ["Martin Havlat", "Patrick Marleau", "Leo Komarov", "Mathew Barzal", "Josh Bailey", "Brock Nelson"], "length": 6, "toi_percentages": [13.8, 3.8, 6.2, 22.9, 28.3], "uniqueness_score": 11.6}, {"path_ids": [8467899, 8466139, 8473463, 8478445, 8471217, 8475754], "path_names": ["Martin Havlat", "Patrick Marleau", "Leo Komarov", "Mathew Barzal", "Andrew Ladd", "Brock Nelson"], "length": 6, "toi_percentages": [13.8, 3.8, 6.2, 4.8, 9.4], "uniqueness_score": 3.8}, {"path_ids": [8467899, 8466139, 8473463, 8478463, 8474573, 8475754], "path_names": ["Martin Havlat", "Patrick Marleau", "Leo Komarov", "Anthony Beauvillier", "Josh Bailey", "Brock Nelson"], "length": 6, "toi_percentages": [13.8, 3.8, 5.8, 25.8, 28.3], "uniqueness_score": 12.1}, {"path_ids": [8467899, 8466139, 8473463, 8478463, 8476409, 8475754], "path_names": ["Martin Havlat", "Patrick Marleau", "Leo Komarov", "Anthony Beauvillier", "Alan Quine", "Brock Nelson"], "length": 6, "toi_percentages": [13.8, 3.8, 5.8, 1.1, 11.4], "uniqueness_score": 3.3}, {"path_ids": [8467899, 8466139, 8473463, 8475231, 8474573, 8475754], "path_names": ["Martin Havlat", "Patrick Marleau", "Leo Komarov", "Casey Cizikas", "Josh Bailey", "Brock Nelson"], "length": 6, "toi_percentages": [13.8, 3.8, 5.6, 5.4, 28.3], "uniqueness_score": 7.8}, {"path_ids": [8467899, 8466139, 8473463, 8475231, 8470644, 8475754], "path_names": ["Martin Havlat", "Patrick Marleau", "Leo Komarov", "Casey Cizikas", "Colin McDonald", "Brock Nelson"], "length": 6, "toi_percentages": [13.8, 3.8, 5.6, 5.4, 9.2], "uniqueness_score": 3.7}, {"path_ids": [8467899, 8466139, 8473463, 8475231, 8476765, 8475754], "path_names": ["Martin Havlat", "Patrick Marleau", "Leo Komarov", "Casey Cizikas", "Mike Halmo", "Brock Nelson"], "length": 6, "toi_percentages": [13.8, 3.8, 5.6, 1.0, 4.2], "uniqueness_score": 1.8}, {"path_ids": [8467899, 8466139, 8473463, 8475231, 8476367, 8475754], "path_names": ["Martin Havlat", "Patrick Marleau", "Leo Komarov", "Casey Cizikas", "John Persson", "Brock Nelson"], "length": 6, "toi_percentages": [13.8, 3.8, 5.6, 0.1, 80.2], "uniqueness_score": 17.6}, {"path_ids": [8467899, 8466139, 8473463, 8474709, 8470644, 8475754], "path_names": ["Martin Havlat", "Patrick Marleau", "Leo Komarov", "Matt Martin", "Colin McDonald", "Brock Nelson"], "length": 6, "toi_percentages": [13.8, 3.8, 5.6, 8.0, 9.2], "uniqueness_score": 4.3}, {"path_ids": [8467899, 8466139, 8473463, 8474709, 8476765, 8475754], "path_names": ["Martin Havlat", "Patrick Marleau", "Leo Komarov", "Matt Martin", "Mike Halmo", "Brock Nelson"], "length": 6, "toi_percentages": [13.8, 3.8, 5.6, 0.3, 4.2], "uniqueness_score": 1.6}, {"path_ids": [8467899, 8466139, 8473463, 8474586, 8471217, 8475754], "path_names": ["Martin Havlat", "Patrick Marleau", "Leo Komarov", "Jordan Eberle", "Andrew Ladd", "Brock Nelson"], "length": 6, "toi_percentages": [13.8, 3.8, 4.9, 2.9, 9.4], "uniqueness_score": 3.1}, {"path_ids": [8467899, 8466139, 8473463, 8476419, 8474573, 8475754], "path_names": ["Martin Havlat", "Patrick Marleau", "Leo Komarov", "Jean-Gabriel Pageau", "Josh Bailey", "Brock Nelson"], "length": 6, "toi_percentages": [13.8, 3.8, 4.2, 5.8, 28.3], "uniqueness_score": 7.6}, {"path_ids": [8467899, 8466139, 8473463, 8473546, 8474573, 8475754], "path_names": ["Martin Havlat", "Patrick Marleau", "Leo Komarov", "Michael Grabner", "Josh Bailey", "Brock Nelson"], "length": 6, "toi_percentages": [13.8, 3.8, 4.1, 4.3, 28.3], "uniqueness_score": 7.2}, {"path_ids": [8467899, 8466139, 8473463, 8473546, 8470644, 8475754], "path_names": ["Martin Havlat", "Patrick Marleau", "Leo Komarov", "Michael Grabner", "Colin McDonald", "Brock Nelson"], "length": 6, "toi_percentages": [13.8, 3.8, 4.1, 4.2, 9.2], "uniqueness_score": 3.2}, {"path_ids": [8467899, 8466139, 8473463, 8475832, 8474573, 8475754], "path_names": ["Martin Havlat", "Patrick Marleau", "Leo Komarov", "Tom Kuhnhackl", "Josh Bailey", "Brock Nelson"], "length": 6, "toi_percentages": [13.8, 3.8, 2.6, 6.3, 28.3], "uniqueness_score": 7.3}, {"path_ids": [8467899, 8466139, 8473463, 8477936, 8474573, 8475754], "path_names": ["Martin Havlat", "Patrick Marleau", "Leo Komarov", "Michael Dal Colle", "Josh Bailey", "Brock Nelson"], "length": 6, "toi_percentages": [13.8, 3.8, 2.5, 26.6, 28.3], "uniqueness_score": 11.6}, {"path_ids": [8467899, 8466139, 8473463, 8471362, 8476458, 8475754], "path_names": ["Martin Havlat", "Patrick Marleau", "Leo Komarov", "Mikhail Grabovski", "Ryan Strome", "Brock Nelson"], "length": 6, "toi_percentages": [13.8, 3.8, 2.2, 17.4, 9.7], "uniqueness_score": 5.7}, {"path_ids": [8467899, 8466139, 8473463, 8471362, 8474573, 8475754], "path_names": ["Martin Havlat", "Patrick Marleau", "Leo Komarov", "Mikhail Grabovski", "Josh Bailey", "Brock Nelson"], "length": 6, "toi_percentages": [13.8, 3.8, 2.2, 8.3, 28.3], "uniqueness_score": 7.7}, {"path_ids": [8467899, 8466139, 8473463, 8477527, 8474573, 8475754], "path_names": ["Martin Havlat", "Patrick Marleau", "Leo Komarov", "Ross Johnston", "Josh Bailey", "Brock Nelson"], "length": 6, "toi_percentages": [13.8, 3.8, 1.6, 7.1, 28.3], "uniqueness_score": 7.3}, {"path_ids": [8467899, 8466139, 8473463, 8479206, 8471217, 8475754], "path_names": ["Martin Havlat", "Patrick Marleau", "Leo Komarov", "Tanner Fritz", "Andrew Ladd", "Brock Nelson"], "length": 6, "toi_percentages": [13.8, 3.8, 0.8, 36.3, 9.4], "uniqueness_score": 9.3}, {"path_ids": [8467899, 8466139, 8473463, 8477959, 8471217, 8475754], "path_names": ["Martin Havlat", "Patrick Marleau", "Leo Komarov", "Joshua Ho-Sang", "Andrew Ladd", "Brock Nelson"], "length": 6, "toi_percentages": [13.8, 3.8, 0.6, 26.6, 9.4], "uniqueness_score": 7.2}, {"path_ids": [8467899, 8466139, 8473463, 8477959, 8476409, 8475754], "path_names": ["Martin Havlat", "Patrick Marleau", "Leo Komarov", "Joshua Ho-Sang", "Alan Quine", "Brock Nelson"], "length": 6, "toi_percentages": [13.8, 3.8, 0.6, 8.2, 11.4], "uniqueness_score": 3.7}, {"path_ids": [8467899, 8466139, 8473463, 8477959, 8474573, 8475754], "path_names": ["Martin Havlat", "Patrick Marleau", "Leo Komarov", "Joshua Ho-Sang", "Josh Bailey", "Brock Nelson"], "length": 6, "toi_percentages": [13.8, 3.8, 0.6, 6.4, 28.3], "uniqueness_score": 6.9}, {"path_ids": [8467899, 8466139, 8473463, 8479526, 8474573, 8475754], "path_names": ["Martin Havlat", "Patrick Marleau", "Leo Komarov", "Otto Koivula", "Josh Bailey", "Brock Nelson"], "length": 6, "toi_percentages": [13.8, 3.8, 0.5, 22.7, 28.3], "uniqueness_score": 10.3}, {"path_ids": [8467899, 8466139, 8473463, 8478367, 8474573, 8475754], "path_names": ["Martin Havlat", "Patrick Marleau", "Leo Komarov", "Cole Bardreau", "Josh Bailey", "Brock Nelson"], "length": 6, "toi_percentages": [13.8, 3.8, 0.1, 9.9, 28.3], "uniqueness_score": 7.6}, {"path_ids": [8467899, 8466139, 8478870, 8477935, 8476409, 8475754], "path_names": ["Martin Havlat", "Patrick Marleau", "Rudolfs Balcers", "Sam Bennett", "Alan Quine", "Brock Nelson"], "length": 6, "toi_percentages": [13.8, 0.9, 4.2, 0.5, 11.4], "uniqueness_score": 2.3}, {"path_ids": [8467899, 8470794, 8475169, 8466140, 8471217, 8475754], "path_names": ["Martin Havlat", "Joe Pavelski", "Evander Kane", "Olli Jokinen", "Andrew Ladd", "Brock Nelson"], "length": 6, "toi_percentages": [12.6, 4.8, 6.1, 6.2, 9.4], "uniqueness_score": 4.0}, {"path_ids": [8467899, 8470794, 8475169, 8471218, 8471217, 8475754], "path_names": ["Martin Havlat", "Joe Pavelski", "Evander Kane", "Blake Wheeler", "Andrew Ladd", "Brock Nelson"], "length": 6, "toi_percentages": [12.6, 4.8, 5.1, 15.7, 9.4], "uniqueness_score": 5.8}, {"path_ids": [8467899, 8470794, 8475169, 8469506, 8470153, 8475754], "path_names": ["Martin Havlat", "Joe Pavelski", "Evander Kane", "Jason Pominville", "Pierre-Marc Bouchard", "Brock Nelson"], "length": 6, "toi_percentages": [12.6, 4.8, 3.1, 0.9, 5.1], "uniqueness_score": 1.4}, {"path_ids": [8467899, 8470794, 8475169, 8473564, 8471217, 8475754], "path_names": ["Martin Havlat", "Joe Pavelski", "Evander Kane", "Michael Frolik", "Andrew Ladd", "Brock Nelson"], "length": 6, "toi_percentages": [12.6, 4.8, 2.8, 10.7, 9.4], "uniqueness_score": 4.3}, {"path_ids": [8467899, 8470794, 8475169, 8471682, 8470153, 8475754], "path_names": ["Martin Havlat", "Joe Pavelski", "Evander Kane", "Devin Setoguchi", "Pierre-Marc Bouchard", "Brock Nelson"], "length": 6, "toi_percentages": [12.6, 4.8, 2.3, 8.6, 5.1], "uniqueness_score": 2.8}, {"path_ids": [8467899, 8470794, 8475169, 8471682, 8471217, 8475754], "path_names": ["Martin Havlat", "Joe Pavelski", "Evander Kane", "Devin Setoguchi", "Andrew Ladd", "Brock Nelson"], "length": 6, "toi_percentages": [12.6, 4.8, 2.3, 5.4, 9.4], "uniqueness_score": 3.1}, {"path_ids": [8467899, 8470794, 8475169, 8479344, 8476458, 8475754], "path_names": ["Martin Havlat", "Joe Pavelski", "Evander Kane", "Jesse Puljujarvi", "Ryan Strome", "Brock Nelson"], "length": 6, "toi_percentages": [12.6, 4.8, 1.8, 6.1, 9.7], "uniqueness_score": 3.2}, {"path_ids": [8467899, 8470794, 8475169, 8475788, 8471217, 8475754], "path_names": ["Martin Havlat", "Joe Pavelski", "Evander Kane", "Alexander Burmistrov", "Andrew Ladd", "Brock Nelson"], "length": 6, "toi_percentages": [12.6, 4.8, 1.7, 6.8, 9.4], "uniqueness_score": 3.2}, {"path_ids": [8467899, 8470794, 8475169, 8467353, 8471217, 8475754], "path_names": ["Martin Havlat", "Joe Pavelski", "Evander Kane", "Nik Antropov", "Andrew Ladd", "Brock Nelson"], "length": 6, "toi_percentages": [12.6, 4.8, 1.6, 18.6, 9.4], "uniqueness_score": 5.7}, {"path_ids": [8467899, 8470794, 8475169, 8468704, 8471217, 8475754], "path_names": ["Martin Havlat", "Joe Pavelski", "Evander Kane", "Antti Miettinen", "Andrew Ladd", "Brock Nelson"], "length": 6, "toi_percentages": [12.6, 4.8, 1.2, 5.1, 9.4], "uniqueness_score": 2.8}, {"path_ids": [8467899, 8470794, 8475169, 8469581, 8471217, 8475754], "path_names": ["Martin Havlat", "Joe Pavelski", "Evander Kane", "Kyle Wellwood", "Andrew Ladd", "Brock Nelson"], "length": 6, "toi_percentages": [12.6, 4.8, 1.1, 4.4, 9.4], "uniqueness_score": 2.6}, {"path_ids": [8467899, 8470794, 8475169, 8470289, 8471217, 8475754], "path_names": ["Martin Havlat", "Joe Pavelski", "Evander Kane", "Jim Slater", "Andrew Ladd", "Brock Nelson"], "length": 6, "toi_percentages": [12.6, 4.8, 0.4, 4.0, 9.4], "uniqueness_score": 2.4}, {"path_ids": [8467899, 8470794, 8475169, 8471451, 8471217, 8475754], "path_names": ["Martin Havlat", "Joe Pavelski", "Evander Kane", "Aaron Gagnon", "Andrew Ladd", "Brock Nelson"], "length": 6, "toi_percentages": [12.6, 4.8, 0.1, 5.3, 9.4], "uniqueness_score": 2.6}, {"path_ids": [8467899, 8470794, 8477406, 8478585, 8476409, 8475754], "path_names": ["Martin Havlat", "Joe Pavelski", "Mattias Janmark", "Derek Ryan", "Alan Quine", "Brock Nelson"], "length": 6, "toi_percentages": [12.6, 2.8, 4.6, 1.0, 11.4], "uniqueness_score": 2.6}, {"path_ids": [8467899, 8470794, 8477450, 8476278, 8476458, 8475754], "path_names": ["Martin Havlat", "Joe Pavelski", "Jason Dickinson", "Colin Blackwell", "Ryan Strome", "Brock Nelson"], "length": 6, "toi_percentages": [12.6, 1.7, 7.5, 8.0, 9.7], "uniqueness_score": 4.1}, {"path_ids": [8467899, 8470794, 8481641, 8475745, 8470153, 8475754], "path_names": ["Martin Havlat", "Joe Pavelski", "Joel Kiviranta", "Charlie Coyle", "Pierre-Marc Bouchard", "Brock Nelson"], "length": 6, "toi_percentages": [12.6, 1.4, 4.0, 0.3, 5.1], "uniqueness_score": 0.7}, {"path_ids": [8467899, 8470794, 8474001, 8470289, 8471217, 8475754], "path_names": ["Martin Havlat", "Joe Pavelski", "TJ Galiardi", "Jim Slater", "Andrew Ladd", "Brock Nelson"], "length": 6, "toi_percentages": [12.6, 0.7, 11.9, 4.0, 9.4], "uniqueness_score": 3.9}, {"path_ids": [8467899, 8470794, 8478528, 8478550, 8476458, 8475754], "path_names": ["Martin Havlat", "Joe Pavelski", "Tanner Kero", "Artemi Panarin", "Ryan Strome", "Brock Nelson"], "length": 6, "toi_percentages": [12.6, 0.4, 7.8, 18.5, 9.7], "uniqueness_score": 6.1}, {"path_ids": [8467899, 8466138, 8474001, 8470289, 8471217, 8475754], "path_names": ["Martin Havlat", "Joe Thornton", "TJ Galiardi", "Jim Slater", "Andrew Ladd", "Brock Nelson"], "length": 6, "toi_percentages": [11.5, 2.1, 11.9, 4.0, 9.4], "uniqueness_score": 4.0}, {"path_ids": [8467899, 8466138, 8475878, 8477935, 8476409, 8475754], "path_names": ["Martin Havlat", "Joe Thornton", "Freddie Hamilton", "Sam Bennett", "Alan Quine", "Brock Nelson"], "length": 6, "toi_percentages": [11.5, 0.3, 5.6, 0.5, 11.4], "uniqueness_score": 2.0}, {"path_ids": [8467899, 8466138, 8480037, 8478366, 8476458, 8475754], "path_names": ["Martin Havlat", "Joe Thornton", "Aleksi Heponiemi", "Frank Vatrano", "Ryan Strome", "Brock Nelson"], "length": 6, "toi_percentages": [11.5, 0.1, 22.4, 25.3, 9.7], "uniqueness_score": 10.3}, {"path_ids": [8467899, 8466138, 8480037, 8477935, 8476409, 8475754], "path_names": ["Martin Havlat", "Joe Thornton", "Aleksi Heponiemi", "Sam Bennett", "Alan Quine", "Brock Nelson"], "length": 6, "toi_percentages": [11.5, 0.1, 4.2, 0.5, 11.4], "uniqueness_score": 1.6}, {"path_ids": [8467899, 8473536, 8476624, 8482109, 8476458, 8475754], "path_names": ["Martin Havlat", "James Sheppard", "Barclay Goodrow", "Alexis Lafreni\u00e8re", "Ryan Strome", "Brock Nelson"], "length": 6, "toi_percentages": [10.2, 13.3, 5.0, 4.6, 9.7], "uniqueness_score": 4.8}, {"path_ids": [8467899, 8473536, 8476624, 8480078, 8476458, 8475754], "path_names": ["Martin Havlat", "James Sheppard", "Barclay Goodrow", "Filip Chytil", "Ryan Strome", "Brock Nelson"], "length": 6, "toi_percentages": [10.2, 13.3, 4.8, 6.6, 9.7], "uniqueness_score": 5.2}, {"path_ids": [8467899, 8473536, 8476624, 8478550, 8476458, 8475754], "path_names": ["Martin Havlat", "James Sheppard", "Barclay Goodrow", "Artemi Panarin", "Ryan Strome", "Brock Nelson"], "length": 6, "toi_percentages": [10.2, 13.3, 4.7, 18.5, 9.7], "uniqueness_score": 7.7}, {"path_ids": [8467899, 8473536, 8476624, 8478211, 8476458, 8475754], "path_names": ["Martin Havlat", "James Sheppard", "Barclay Goodrow", "Dryden Hunt", "Ryan Strome", "Brock Nelson"], "length": 6, "toi_percentages": [10.2, 13.3, 1.1, 13.8, 9.7], "uniqueness_score": 5.9}, {"path_ids": [8467899, 8473536, 8476624, 8480833, 8476458, 8475754], "path_names": ["Martin Havlat", "James Sheppard", "Barclay Goodrow", "Vitali Kravtsov", "Ryan Strome", "Brock Nelson"], "length": 6, "toi_percentages": [10.2, 13.3, 0.5, 7.7, 9.7], "uniqueness_score": 4.5}, {"path_ids": [8467899, 8473536, 8470854, 8475855, 8476458, 8475754], "path_names": ["Martin Havlat", "James Sheppard", "Tanner Glass", "Jesper Fast", "Ryan Strome", "Brock Nelson"], "length": 6, "toi_percentages": [10.2, 7.7, 10.7, 7.8, 9.7], "uniqueness_score": 5.5}, {"path_ids": [8467899, 8473536, 8468575, 8475855, 8476458, 8475754], "path_names": ["Martin Havlat", "James Sheppard", "Dominic Moore", "Jesper Fast", "Ryan Strome", "Brock Nelson"], "length": 6, "toi_percentages": [10.2, 6.4, 13.6, 7.8, 9.7], "uniqueness_score": 5.8}, {"path_ids": [8467899, 8467351, 8474641, 8478873, 8476458, 8475754], "path_names": ["Martin Havlat", "Scott Gomez", "Adam Henrique", "Troy Terry", "Ryan Strome", "Brock Nelson"], "length": 6, "toi_percentages": [9.5, 17.9, 12.9, 21.1, 9.7], "uniqueness_score": 10.8}, {"path_ids": [8467899, 8467351, 8474641, 8481533, 8476458, 8475754], "path_names": ["Martin Havlat", "Scott Gomez", "Adam Henrique", "Trevor Zegras", "Ryan Strome", "Brock Nelson"], "length": 6, "toi_percentages": [9.5, 17.9, 6.4, 21.5, 9.7], "uniqueness_score": 9.5}, {"path_ids": [8467899, 8467351, 8474641, 8478366, 8476458, 8475754], "path_names": ["Martin Havlat", "Scott Gomez", "Adam Henrique", "Frank Vatrano", "Ryan Strome", "Brock Nelson"], "length": 6, "toi_percentages": [9.5, 17.9, 2.7, 25.3, 9.7], "uniqueness_score": 9.5}, {"path_ids": [8467899, 8467351, 8474641, 8482745, 8476458, 8475754], "path_names": ["Martin Havlat", "Scott Gomez", "Adam Henrique", "Mason McTavish", "Ryan Strome", "Brock Nelson"], "length": 6, "toi_percentages": [9.5, 17.9, 2.3, 19.7, 9.7], "uniqueness_score": 8.2}, {"path_ids": [8467899, 8467351, 8474641, 8480031, 8476458, 8475754], "path_names": ["Martin Havlat", "Scott Gomez", "Adam Henrique", "Maxime Comtois", "Ryan Strome", "Brock Nelson"], "length": 6, "toi_percentages": [9.5, 17.9, 2.2, 7.4, 9.7], "uniqueness_score": 5.6}, {"path_ids": [8467899, 8467351, 8474641, 8484153, 8476458, 8475754], "path_names": ["Martin Havlat", "Scott Gomez", "Adam Henrique", "Leo Carlsson", "Ryan Strome", "Brock Nelson"], "length": 6, "toi_percentages": [9.5, 17.9, 1.1, 12.8, 9.7], "uniqueness_score": 6.5}, {"path_ids": [8467899, 8467351, 8474641, 8481517, 8476458, 8475754], "path_names": ["Martin Havlat", "Scott Gomez", "Adam Henrique", "Brett Leason", "Ryan Strome", "Brock Nelson"], "length": 6, "toi_percentages": [9.5, 17.9, 0.7, 6.2, 9.7], "uniqueness_score": 5.1}, {"path_ids": [8467899, 8467351, 8470609, 8473579, 8476458, 8475754], "path_names": ["Martin Havlat", "Scott Gomez", "Steve Bernier", "Nikolay Kulemin", "Ryan Strome", "Brock Nelson"], "length": 6, "toi_percentages": [9.5, 16.5, 5.4, 8.3, 9.7], "uniqueness_score": 6.2}, {"path_ids": [8467899, 8467351, 8470609, 8473579, 8474573, 8475754], "path_names": ["Martin Havlat", "Scott Gomez", "Steve Bernier", "Nikolay Kulemin", "Josh Bailey", "Brock Nelson"], "length": 6, "toi_percentages": [9.5, 16.5, 5.4, 5.8, 28.3], "uniqueness_score": 9.6}, {"path_ids": [8467899, 8467351, 8470609, 8473579, 8476409, 8475754], "path_names": ["Martin Havlat", "Scott Gomez", "Steve Bernier", "Nikolay Kulemin", "Alan Quine", "Brock Nelson"], "length": 6, "toi_percentages": [9.5, 16.5, 5.4, 1.7, 11.4], "uniqueness_score": 5.2}, {"path_ids": [8467899, 8467351, 8470609, 8471362, 8476458, 8475754], "path_names": ["Martin Havlat", "Scott Gomez", "Steve Bernier", "Mikhail Grabovski", "Ryan Strome", "Brock Nelson"], "length": 6, "toi_percentages": [9.5, 16.5, 5.3, 17.4, 9.7], "uniqueness_score": 8.1}, {"path_ids": [8467899, 8467351, 8470609, 8471362, 8474573, 8475754], "path_names": ["Martin Havlat", "Scott Gomez", "Steve Bernier", "Mikhail Grabovski", "Josh Bailey", "Brock Nelson"], "length": 6, "toi_percentages": [9.5, 16.5, 5.3, 8.3, 28.3], "uniqueness_score": 10.1}, {"path_ids": [8467899, 8467351, 8470609, 8476386, 8476458, 8475754], "path_names": ["Martin Havlat", "Scott Gomez", "Steve Bernier", "Shane Prince", "Ryan Strome", "Brock Nelson"], "length": 6, "toi_percentages": [9.5, 16.5, 2.5, 19.9, 9.7], "uniqueness_score": 8.0}, {"path_ids": [8467899, 8467351, 8470609, 8476386, 8471217, 8475754], "path_names": ["Martin Havlat", "Scott Gomez", "Steve Bernier", "Shane Prince", "Andrew Ladd", "Brock Nelson"], "length": 6, "toi_percentages": [9.5, 16.5, 2.5, 9.2, 9.4], "uniqueness_score": 5.7}, {"path_ids": [8467899, 8467351, 8470609, 8476386, 8476409, 8475754], "path_names": ["Martin Havlat", "Scott Gomez", "Steve Bernier", "Shane Prince", "Alan Quine", "Brock Nelson"], "length": 6, "toi_percentages": [9.5, 16.5, 2.5, 9.0, 11.4], "uniqueness_score": 6.1}, {"path_ids": [8467899, 8467351, 8470609, 8476386, 8474573, 8475754], "path_names": ["Martin Havlat", "Scott Gomez", "Steve Bernier", "Shane Prince", "Josh Bailey", "Brock Nelson"], "length": 6, "toi_percentages": [9.5, 16.5, 2.5, 6.4, 28.3], "uniqueness_score": 9.1}, {"path_ids": [8467899, 8467351, 8470609, 8460720, 8470644, 8475754], "path_names": ["Martin Havlat", "Scott Gomez", "Steve Bernier", "Eric Boulton", "Colin McDonald", "Brock Nelson"], "length": 6, "toi_percentages": [9.5, 16.5, 0.7, 7.6, 9.2], "uniqueness_score": 4.9}, {"path_ids": [8467899, 8467351, 8470609, 8460720, 8476458, 8475754], "path_names": ["Martin Havlat", "Scott Gomez", "Steve Bernier", "Eric Boulton", "Ryan Strome", "Brock Nelson"], "length": 6, "toi_percentages": [9.5, 16.5, 0.7, 6.1, 9.7], "uniqueness_score": 4.7}, {"path_ids": [8467899, 8467351, 8470609, 8460720, 8476765, 8475754], "path_names": ["Martin Havlat", "Scott Gomez", "Steve Bernier", "Eric Boulton", "Mike Halmo", "Brock Nelson"], "length": 6, "toi_percentages": [9.5, 16.5, 0.7, 3.8, 4.2], "uniqueness_score": 3.1}, {"path_ids": [8467899, 8467351, 8470176, 8470803, 8470153, 8475754], "path_names": ["Martin Havlat", "Scott Gomez", "Sean Bergenheim", "Kyle Brodziak", "Pierre-Marc Bouchard", "Brock Nelson"], "length": 6, "toi_percentages": [9.5, 6.6, 5.1, 3.8, 5.1], "uniqueness_score": 2.1}, {"path_ids": [8467899, 8467351, 8469500, 8477415, 8476458, 8475754], "path_names": ["Martin Havlat", "Scott Gomez", "Michael Cammalleri", "Anton Slepyshev", "Ryan Strome", "Brock Nelson"], "length": 6, "toi_percentages": [9.5, 5.5, 1.4, 12.1, 9.7], "uniqueness_score": 3.8}, {"path_ids": [8467899, 8467351, 8468504, 8475166, 8474573, 8475754], "path_names": ["Martin Havlat", "Scott Gomez", "Brad Boyes", "John Tavares", "Josh Bailey", "Brock Nelson"], "length": 6, "toi_percentages": [9.5, 5.4, 19.6, 18.2, 28.3], "uniqueness_score": 12.8}, {"path_ids": [8467899, 8467351, 8468504, 8475166, 8476458, 8475754], "path_names": ["Martin Havlat", "Scott Gomez", "Brad Boyes", "John Tavares", "Ryan Strome", "Brock Nelson"], "length": 6, "toi_percentages": [9.5, 5.4, 19.6, 5.9, 9.7], "uniqueness_score": 6.3}, {"path_ids": [8467899, 8467351, 8468504, 8475166, 8471217, 8475754], "path_names": ["Martin Havlat", "Scott Gomez", "Brad Boyes", "John Tavares", "Andrew Ladd", "Brock Nelson"], "length": 6, "toi_percentages": [9.5, 5.4, 19.6, 2.0, 9.4], "uniqueness_score": 5.5}, {"path_ids": [8467899, 8467351, 8468504, 8475166, 8476409, 8475754], "path_names": ["Martin Havlat", "Scott Gomez", "Brad Boyes", "John Tavares", "Alan Quine", "Brock Nelson"], "length": 6, "toi_percentages": [9.5, 5.4, 19.6, 0.7, 11.4], "uniqueness_score": 5.6}, {"path_ids": [8467899, 8467351, 8468504, 8475166, 8470644, 8475754], "path_names": ["Martin Havlat", "Scott Gomez", "Brad Boyes", "John Tavares", "Colin McDonald", "Brock Nelson"], "length": 6, "toi_percentages": [9.5, 5.4, 19.6, 0.4, 9.2], "uniqueness_score": 5.1}, {"path_ids": [8467899, 8467351, 8468504, 8475166, 8470153, 8475754], "path_names": ["Martin Havlat", "Scott Gomez", "Brad Boyes", "John Tavares", "Pierre-Marc Bouchard", "Brock Nelson"], "length": 6, "toi_percentages": [9.5, 5.4, 19.6, 0.3, 5.1], "uniqueness_score": 4.2}, {"path_ids": [8467899, 8467351, 8468504, 8473546, 8474573, 8475754], "path_names": ["Martin Havlat", "Scott Gomez", "Brad Boyes", "Michael Grabner", "Josh Bailey", "Brock Nelson"], "length": 6, "toi_percentages": [9.5, 5.4, 4.6, 4.3, 28.3], "uniqueness_score": 6.8}, {"path_ids": [8467899, 8467351, 8468504, 8473546, 8470644, 8475754], "path_names": ["Martin Havlat", "Scott Gomez", "Brad Boyes", "Michael Grabner", "Colin McDonald", "Brock Nelson"], "length": 6, "toi_percentages": [9.5, 5.4, 4.6, 4.2, 9.2], "uniqueness_score": 2.7}, {"path_ids": [8467899, 8467351, 8468504, 8469779, 8470644, 8475754], "path_names": ["Martin Havlat", "Scott Gomez", "Brad Boyes", "Keith Aucoin", "Colin McDonald", "Brock Nelson"], "length": 6, "toi_percentages": [9.5, 5.4, 0.6, 57.5, 9.2], "uniqueness_score": 13.1}, {"path_ids": [8467899, 8467351, 8468504, 8469779, 8474573, 8475754], "path_names": ["Martin Havlat", "Scott Gomez", "Brad Boyes", "Keith Aucoin", "Josh Bailey", "Brock Nelson"], "length": 6, "toi_percentages": [9.5, 5.4, 0.6, 12.5, 28.3], "uniqueness_score": 7.6}, {"path_ids": [8467899, 8467351, 8470105, 8470803, 8470153, 8475754], "path_names": ["Martin Havlat", "Scott Gomez", "Scottie Upshall", "Kyle Brodziak", "Pierre-Marc Bouchard", "Brock Nelson"], "length": 6, "toi_percentages": [9.5, 5.1, 34.2, 3.8, 5.1], "uniqueness_score": 7.9}, {"path_ids": [8467899, 8467351, 8477952, 8482745, 8476458, 8475754], "path_names": ["Martin Havlat", "Scott Gomez", "Robby Fabbri", "Mason McTavish", "Ryan Strome", "Brock Nelson"], "length": 6, "toi_percentages": [9.5, 4.3, 6.2, 19.7, 9.7], "uniqueness_score": 6.2}, {"path_ids": [8467899, 8467351, 8477952, 8483445, 8476458, 8475754], "path_names": ["Martin Havlat", "Scott Gomez", "Robby Fabbri", "Cutter Gauthier", "Ryan Strome", "Brock Nelson"], "length": 6, "toi_percentages": [9.5, 4.3, 5.3, 6.4, 9.7], "uniqueness_score": 3.2}, {"path_ids": [8467899, 8467351, 8477952, 8484153, 8476458, 8475754], "path_names": ["Martin Havlat", "Scott Gomez", "Robby Fabbri", "Leo Carlsson", "Ryan Strome", "Brock Nelson"], "length": 6, "toi_percentages": [9.5, 4.3, 1.7, 12.8, 9.7], "uniqueness_score": 3.8}, {"path_ids": [8467899, 8467351, 8474001, 8470289, 8471217, 8475754], "path_names": ["Martin Havlat", "Scott Gomez", "TJ Galiardi", "Jim Slater", "Andrew Ladd", "Brock Nelson"], "length": 6, "toi_percentages": [9.5, 3.9, 11.9, 4.0, 9.4], "uniqueness_score": 3.9}, {"path_ids": [8467899, 8467351, 8470156, 8466251, 8476409, 8475754], "path_names": ["Martin Havlat", "Scott Gomez", "Joey Crabb", "Jason Chimera", "Alan Quine", "Brock Nelson"], "length": 6, "toi_percentages": [9.5, 1.2, 8.8, 8.3, 11.4], "uniqueness_score": 4.0}, {"path_ids": [8467899, 8467351, 8470156, 8466251, 8471217, 8475754], "path_names": ["Martin Havlat", "Scott Gomez", "Joey Crabb", "Jason Chimera", "Andrew Ladd", "Brock Nelson"], "length": 6, "toi_percentages": [9.5, 1.2, 8.8, 8.1, 9.4], "uniqueness_score": 3.6}, {"path_ids": [8467899, 8469622, 8474641, 8478873, 8476458, 8475754], "path_names": ["Martin Havlat", "Ryane Clowe", "Adam Henrique", "Troy Terry", "Ryan Strome", "Brock Nelson"], "length": 6, "toi_percentages": [7.3, 29.9, 12.9, 21.1, 9.7], "uniqueness_score": 12.8}, {"path_ids": [8467899, 8469622, 8474641, 8481533, 8476458, 8475754], "path_names": ["Martin Havlat", "Ryane Clowe", "Adam Henrique", "Trevor Zegras", "Ryan Strome", "Brock Nelson"], "length": 6, "toi_percentages": [7.3, 29.9, 6.4, 21.5, 9.7], "uniqueness_score": 11.5}, {"path_ids": [8467899, 8469622, 8474641, 8478366, 8476458, 8475754], "path_names": ["Martin Havlat", "Ryane Clowe", "Adam Henrique", "Frank Vatrano", "Ryan Strome", "Brock Nelson"], "length": 6, "toi_percentages": [7.3, 29.9, 2.7, 25.3, 9.7], "uniqueness_score": 11.6}, {"path_ids": [8467899, 8469622, 8474641, 8482745, 8476458, 8475754], "path_names": ["Martin Havlat", "Ryane Clowe", "Adam Henrique", "Mason McTavish", "Ryan Strome", "Brock Nelson"], "length": 6, "toi_percentages": [7.3, 29.9, 2.3, 19.7, 9.7], "uniqueness_score": 10.3}, {"path_ids": [8467899, 8469622, 8474641, 8480031, 8476458, 8475754], "path_names": ["Martin Havlat", "Ryane Clowe", "Adam Henrique", "Maxime Comtois", "Ryan Strome", "Brock Nelson"], "length": 6, "toi_percentages": [7.3, 29.9, 2.2, 7.4, 9.7], "uniqueness_score": 7.7}, {"path_ids": [8467899, 8469622, 8474641, 8484153, 8476458, 8475754], "path_names": ["Martin Havlat", "Ryane Clowe", "Adam Henrique", "Leo Carlsson", "Ryan Strome", "Brock Nelson"], "length": 6, "toi_percentages": [7.3, 29.9, 1.1, 12.8, 9.7], "uniqueness_score": 8.6}, {"path_ids": [8467899, 8469622, 8474641, 8481517, 8476458, 8475754], "path_names": ["Martin Havlat", "Ryane Clowe", "Adam Henrique", "Brett Leason", "Ryan Strome", "Brock Nelson"], "length": 6, "toi_percentages": [7.3, 29.9, 0.7, 6.2, 9.7], "uniqueness_score": 7.1}, {"path_ids": [8467899, 8469622, 8467389, 8475184, 8476458, 8475754], "path_names": ["Martin Havlat", "Ryane Clowe", "Brad Richards", "Chris Kreider", "Ryan Strome", "Brock Nelson"], "length": 6, "toi_percentages": [7.3, 7.3, 6.2, 6.9, 9.7], "uniqueness_score": 3.7}, {"path_ids": [8467899, 8469622, 8473544, 8475184, 8476458, 8475754], "path_names": ["Martin Havlat", "Ryane Clowe", "Derick Brassard", "Chris Kreider", "Ryan Strome", "Brock Nelson"], "length": 6, "toi_percentages": [7.3, 6.4, 5.0, 6.9, 9.7], "uniqueness_score": 3.2}, {"path_ids": [8467899, 8469622, 8473544, 8478463, 8474573, 8475754], "path_names": ["Martin Havlat", "Ryane Clowe", "Derick Brassard", "Anthony Beauvillier", "Josh Bailey", "Brock Nelson"], "length": 6, "toi_percentages": [7.3, 6.4, 3.7, 25.8, 28.3], "uniqueness_score": 10.8}, {"path_ids": [8467899, 8469622, 8473544, 8478463, 8476409, 8475754], "path_names": ["Martin Havlat", "Ryane Clowe", "Derick Brassard", "Anthony Beauvillier", "Alan Quine", "Brock Nelson"], "length": 6, "toi_percentages": [7.3, 6.4, 3.7, 1.1, 11.4], "uniqueness_score": 2.1}, {"path_ids": [8467899, 8469622, 8473544, 8477936, 8474573, 8475754], "path_names": ["Martin Havlat", "Ryane Clowe", "Derick Brassard", "Michael Dal Colle", "Josh Bailey", "Brock Nelson"], "length": 6, "toi_percentages": [7.3, 6.4, 1.5, 26.6, 28.3], "uniqueness_score": 10.5}, {"path_ids": [8467899, 8469622, 8473544, 8475832, 8474573, 8475754], "path_names": ["Martin Havlat", "Ryane Clowe", "Derick Brassard", "Tom Kuhnhackl", "Josh Bailey", "Brock Nelson"], "length": 6, "toi_percentages": [7.3, 6.4, 1.2, 6.3, 28.3], "uniqueness_score": 6.2}, {"path_ids": [8467899, 8469622, 8473544, 8479526, 8474573, 8475754], "path_names": ["Martin Havlat", "Ryane Clowe", "Derick Brassard", "Otto Koivula", "Josh Bailey", "Brock Nelson"], "length": 6, "toi_percentages": [7.3, 6.4, 0.1, 22.7, 28.3], "uniqueness_score": 9.4}, {"path_ids": [8467899, 8469622, 8473544, 8478367, 8474573, 8475754], "path_names": ["Martin Havlat", "Ryane Clowe", "Derick Brassard", "Cole Bardreau", "Josh Bailey", "Brock Nelson"], "length": 6, "toi_percentages": [7.3, 6.4, 0.0, 9.9, 28.3], "uniqueness_score": 6.7}, {"path_ids": [8467899, 8469622, 8475692, 8475184, 8476458, 8475754], "path_names": ["Martin Havlat", "Ryane Clowe", "Mats Zuccarello", "Chris Kreider", "Ryan Strome", "Brock Nelson"], "length": 6, "toi_percentages": [7.3, 5.0, 16.0, 6.9, 9.7], "uniqueness_score": 5.2}, {"path_ids": [8467899, 8469622, 8475692, 8476459, 8476458, 8475754], "path_names": ["Martin Havlat", "Ryane Clowe", "Mats Zuccarello", "Mika Zibanejad", "Ryan Strome", "Brock Nelson"], "length": 6, "toi_percentages": [7.3, 5.0, 9.5, 4.6, 9.7], "uniqueness_score": 3.4}, {"path_ids": [8467899, 8469622, 8475692, 8476922, 8476458, 8475754], "path_names": ["Martin Havlat", "Ryane Clowe", "Mats Zuccarello", "Boo Nieves", "Ryan Strome", "Brock Nelson"], "length": 6, "toi_percentages": [7.3, 5.0, 0.2, 9.2, 9.7], "uniqueness_score": 2.4}, {"path_ids": [8467899, 8469622, 8470041, 8475184, 8476458, 8475754], "path_names": ["Martin Havlat", "Ryane Clowe", "Rick Nash", "Chris Kreider", "Ryan Strome", "Brock Nelson"], "length": 6, "toi_percentages": [7.3, 4.9, 13.9, 6.9, 9.7], "uniqueness_score": 4.8}, {"path_ids": [8467899, 8469622, 8470041, 8476459, 8476458, 8475754], "path_names": ["Martin Havlat", "Ryane Clowe", "Rick Nash", "Mika Zibanejad", "Ryan Strome", "Brock Nelson"], "length": 6, "toi_percentages": [7.3, 4.9, 9.7, 4.6, 9.7], "uniqueness_score": 3.4}, {"path_ids": [8467899, 8469622, 8470041, 8477402, 8476458, 8475754], "path_names": ["Martin Havlat", "Ryane Clowe", "Rick Nash", "Pavel Buchnevich", "Ryan Strome", "Brock Nelson"], "length": 6, "toi_percentages": [7.3, 4.9, 4.4, 4.4, 9.7], "uniqueness_score": 2.3}, {"path_ids": [8467899, 8469622, 8472410, 8473504, 8474573, 8475754], "path_names": ["Martin Havlat", "Ryane Clowe", "Stephen Gionta", "Cal Clutterbuck", "Josh Bailey", "Brock Nelson"], "length": 6, "toi_percentages": [7.3, 4.8, 4.3, 4.7, 28.3], "uniqueness_score": 6.2}, {"path_ids": [8467899, 8469622, 8472410, 8473504, 8470153, 8475754], "path_names": ["Martin Havlat", "Ryane Clowe", "Stephen Gionta", "Cal Clutterbuck", "Pierre-Marc Bouchard", "Brock Nelson"], "length": 6, "toi_percentages": [7.3, 4.8, 4.3, 2.2, 5.1], "uniqueness_score": 0.8}, {"path_ids": [8467899, 8469622, 8472410, 8473504, 8476409, 8475754], "path_names": ["Martin Havlat", "Ryane Clowe", "Stephen Gionta", "Cal Clutterbuck", "Alan Quine", "Brock Nelson"], "length": 6, "toi_percentages": [7.3, 4.8, 4.3, 0.9, 11.4], "uniqueness_score": 1.8}, {"path_ids": [8467899, 8469622, 8472410, 8473504, 8476367, 8475754], "path_names": ["Martin Havlat", "Ryane Clowe", "Stephen Gionta", "Cal Clutterbuck", "John Persson", "Brock Nelson"], "length": 6, "toi_percentages": [7.3, 4.8, 4.3, 0.5, 80.2], "uniqueness_score": 16.2}, {"path_ids": [8467899, 8469622, 8472410, 8477881, 8476409, 8475754], "path_names": ["Martin Havlat", "Ryane Clowe", "Stephen Gionta", "Connor Jones", "Alan Quine", "Brock Nelson"], "length": 6, "toi_percentages": [7.3, 4.8, 0.8, 4.9, 11.4], "uniqueness_score": 1.9}, {"path_ids": [8467899, 8469622, 8472410, 8477881, 8474573, 8475754], "path_names": ["Martin Havlat", "Ryane Clowe", "Stephen Gionta", "Connor Jones", "Josh Bailey", "Brock Nelson"], "length": 6, "toi_percentages": [7.3, 4.8, 0.8, 4.9, 28.3], "uniqueness_score": 5.5}, {"path_ids": [8467899, 8471311, 8465951, 8470803, 8470153, 8475754], "path_names": ["Martin Havlat", "Tyler Kennedy", "Matt Cooke", "Kyle Brodziak", "Pierre-Marc Bouchard", "Brock Nelson"], "length": 6, "toi_percentages": [6.6, 12.3, 46.7, 3.8, 5.1], "uniqueness_score": 11.5}, {"path_ids": [8467899, 8471311, 8465951, 8475745, 8470153, 8475754], "path_names": ["Martin Havlat", "Tyler Kennedy", "Matt Cooke", "Charlie Coyle", "Pierre-Marc Bouchard", "Brock Nelson"], "length": 6, "toi_percentages": [6.6, 12.3, 4.3, 0.3, 5.1], "uniqueness_score": 1.8}, {"path_ids": [8467899, 8471311, 8465951, 8468482, 8470153, 8475754], "path_names": ["Martin Havlat", "Tyler Kennedy", "Matt Cooke", "Dany Heatley", "Pierre-Marc Bouchard", "Brock Nelson"], "length": 6, "toi_percentages": [6.6, 12.3, 3.1, 5.9, 5.1], "uniqueness_score": 2.7}, {"path_ids": [8467899, 8471311, 8474641, 8478873, 8476458, 8475754], "path_names": ["Martin Havlat", "Tyler Kennedy", "Adam Henrique", "Troy Terry", "Ryan Strome", "Brock Nelson"], "length": 6, "toi_percentages": [6.6, 7.8, 12.9, 21.1, 9.7], "uniqueness_score": 8.0}, {"path_ids": [8467899, 8471311, 8474641, 8481533, 8476458, 8475754], "path_names": ["Martin Havlat", "Tyler Kennedy", "Adam Henrique", "Trevor Zegras", "Ryan Strome", "Brock Nelson"], "length": 6, "toi_percentages": [6.6, 7.8, 6.4, 21.5, 9.7], "uniqueness_score": 6.7}, {"path_ids": [8467899, 8471311, 8474641, 8478366, 8476458, 8475754], "path_names": ["Martin Havlat", "Tyler Kennedy", "Adam Henrique", "Frank Vatrano", "Ryan Strome", "Brock Nelson"], "length": 6, "toi_percentages": [6.6, 7.8, 2.7, 25.3, 9.7], "uniqueness_score": 6.8}, {"path_ids": [8467899, 8471311, 8474641, 8482745, 8476458, 8475754], "path_names": ["Martin Havlat", "Tyler Kennedy", "Adam Henrique", "Mason McTavish", "Ryan Strome", "Brock Nelson"], "length": 6, "toi_percentages": [6.6, 7.8, 2.3, 19.7, 9.7], "uniqueness_score": 5.5}, {"path_ids": [8467899, 8471311, 8474641, 8480031, 8476458, 8475754], "path_names": ["Martin Havlat", "Tyler Kennedy", "Adam Henrique", "Maxime Comtois", "Ryan Strome", "Brock Nelson"], "length": 6, "toi_percentages": [6.6, 7.8, 2.2, 7.4, 9.7], "uniqueness_score": 2.9}, {"path_ids": [8467899, 8471311, 8474641, 8484153, 8476458, 8475754], "path_names": ["Martin Havlat", "Tyler Kennedy", "Adam Henrique", "Leo Carlsson", "Ryan Strome", "Brock Nelson"], "length": 6, "toi_percentages": [6.6, 7.8, 1.1, 12.8, 9.7], "uniqueness_score": 3.8}, {"path_ids": [8467899, 8471311, 8474641, 8481517, 8476458, 8475754], "path_names": ["Martin Havlat", "Tyler Kennedy", "Adam Henrique", "Brett Leason", "Ryan Strome", "Brock Nelson"], "length": 6, "toi_percentages": [6.6, 7.8, 0.7, 6.2, 9.7], "uniqueness_score": 2.3}, {"path_ids": [8467899, 8471311, 8474024, 8471299, 8470153, 8475754], "path_names": ["Martin Havlat", "Tyler Kennedy", "Jim O'Brien", "Peter Regin", "Pierre-Marc Bouchard", "Brock Nelson"], "length": 6, "toi_percentages": [6.6, 1.2, 20.5, 12.8, 5.1], "uniqueness_score": 5.5}, {"path_ids": [8467899, 8471311, 8474024, 8471299, 8474573, 8475754], "path_names": ["Martin Havlat", "Tyler Kennedy", "Jim O'Brien", "Peter Regin", "Josh Bailey", "Brock Nelson"], "length": 6, "toi_percentages": [6.6, 1.2, 20.5, 11.0, 28.3], "uniqueness_score": 10.0}, {"path_ids": [8467899, 8471311, 8474024, 8471299, 8470644, 8475754], "path_names": ["Martin Havlat", "Tyler Kennedy", "Jim O'Brien", "Peter Regin", "Colin McDonald", "Brock Nelson"], "length": 6, "toi_percentages": [6.6, 1.2, 20.5, 5.1, 9.2], "uniqueness_score": 4.8}, {"path_ids": [8467899, 8471311, 8474024, 8476459, 8476458, 8475754], "path_names": ["Martin Havlat", "Tyler Kennedy", "Jim O'Brien", "Mika Zibanejad", "Ryan Strome", "Brock Nelson"], "length": 6, "toi_percentages": [6.6, 1.2, 7.9, 4.6, 9.7], "uniqueness_score": 2.1}, {"path_ids": [8467899, 8471956, 8475323, 8473564, 8471217, 8475754], "path_names": ["Martin Havlat", "Andrew Desjardins", "Marcus Kruger", "Michael Frolik", "Andrew Ladd", "Brock Nelson"], "length": 6, "toi_percentages": [5.6, 18.3, 8.2, 10.7, 9.4], "uniqueness_score": 6.8}, {"path_ids": [8467899, 8471956, 8473722, 8469820, 8470153, 8475754], "path_names": ["Martin Havlat", "Andrew Desjardins", "John Scott", "Zenon Konopka", "Pierre-Marc Bouchard", "Brock Nelson"], "length": 6, "toi_percentages": [5.6, 3.3, 8.4, 4.0, 5.1], "uniqueness_score": 1.3}, {"path_ids": [8467899, 8471956, 8478528, 8478550, 8476458, 8475754], "path_names": ["Martin Havlat", "Andrew Desjardins", "Tanner Kero", "Artemi Panarin", "Ryan Strome", "Brock Nelson"], "length": 6, "toi_percentages": [5.6, 2.2, 7.8, 18.5, 9.7], "uniqueness_score": 5.0}, {"path_ids": [8467899, 8471956, 8475878, 8477935, 8476409, 8475754], "path_names": ["Martin Havlat", "Andrew Desjardins", "Freddie Hamilton", "Sam Bennett", "Alan Quine", "Brock Nelson"], "length": 6, "toi_percentages": [5.6, 0.7, 5.6, 0.5, 11.4], "uniqueness_score": 0.8}, {"path_ids": [8467899, 8476442, 8474009, 8475832, 8474573, 8475754], "path_names": ["Martin Havlat", "Matt Nieto", "Nick Bonino", "Tom Kuhnhackl", "Josh Bailey", "Brock Nelson"], "length": 6, "toi_percentages": [4.2, 6.9, 1.3, 6.3, 28.3], "uniqueness_score": 5.7}, {"path_ids": [8467899, 8476442, 8478569, 8478366, 8476458, 8475754], "path_names": ["Martin Havlat", "Matt Nieto", "Noel Acciari", "Frank Vatrano", "Ryan Strome", "Brock Nelson"], "length": 6, "toi_percentages": [4.2, 5.2, 4.1, 25.3, 9.7], "uniqueness_score": 6.0}, {"path_ids": [8467899, 8476442, 8478569, 8478211, 8476458, 8475754], "path_names": ["Martin Havlat", "Matt Nieto", "Noel Acciari", "Dryden Hunt", "Ryan Strome", "Brock Nelson"], "length": 6, "toi_percentages": [4.2, 5.2, 2.1, 13.8, 9.7], "uniqueness_score": 3.2}, {"path_ids": [8467899, 8476442, 8477930, 8480087, 8470644, 8475754], "path_names": ["Martin Havlat", "Matt Nieto", "Pierre-Edouard Bellemare", "Mike Vecchione", "Colin McDonald", "Brock Nelson"], "length": 6, "toi_percentages": [4.2, 5.1, 0.1, 35.5, 9.2], "uniqueness_score": 7.2}, {"path_ids": [8467899, 8476442, 8468208, 8466251, 8476409, 8475754], "path_names": ["Martin Havlat", "Matt Nieto", "Joel Ward", "Jason Chimera", "Alan Quine", "Brock Nelson"], "length": 6, "toi_percentages": [4.2, 4.2, 24.7, 8.3, 11.4], "uniqueness_score": 6.9}, {"path_ids": [8467899, 8476442, 8468208, 8466251, 8471217, 8475754], "path_names": ["Martin Havlat", "Matt Nieto", "Joel Ward", "Jason Chimera", "Andrew Ladd", "Brock Nelson"], "length": 6, "toi_percentages": [4.2, 4.2, 24.7, 8.1, 9.4], "uniqueness_score": 6.4}, {"path_ids": [8467899, 8476442, 8468208, 8471362, 8476458, 8475754], "path_names": ["Martin Havlat", "Matt Nieto", "Joel Ward", "Mikhail Grabovski", "Ryan Strome", "Brock Nelson"], "length": 6, "toi_percentages": [4.2, 4.2, 3.4, 17.4, 9.7], "uniqueness_score": 4.0}, {"path_ids": [8467899, 8476442, 8468208, 8471362, 8474573, 8475754], "path_names": ["Martin Havlat", "Matt Nieto", "Joel Ward", "Mikhail Grabovski", "Josh Bailey", "Brock Nelson"], "length": 6, "toi_percentages": [4.2, 4.2, 3.4, 8.3, 28.3], "uniqueness_score": 6.0}, {"path_ids": [8467899, 8476442, 8479370, 8473449, 8474573, 8475754], "path_names": ["Martin Havlat", "Matt Nieto", "Tyson Jost", "Kyle Okposo", "Josh Bailey", "Brock Nelson"], "length": 6, "toi_percentages": [4.2, 2.9, 4.6, 9.9, 28.3], "uniqueness_score": 6.3}, {"path_ids": [8467899, 8476442, 8479370, 8473449, 8476409, 8475754], "path_names": ["Martin Havlat", "Matt Nieto", "Tyson Jost", "Kyle Okposo", "Alan Quine", "Brock Nelson"], "length": 6, "toi_percentages": [4.2, 2.9, 4.6, 0.5, 11.4], "uniqueness_score": 0.8}, {"path_ids": [8467899, 8476442, 8479370, 8473449, 8470153, 8475754], "path_names": ["Martin Havlat", "Matt Nieto", "Tyson Jost", "Kyle Okposo", "Pierre-Marc Bouchard", "Brock Nelson"], "length": 6, "toi_percentages": [4.2, 2.9, 4.6, 0.3, 5.1], "uniqueness_score": 0.0}, {"path_ids": [8467899, 8476442, 8475268, 8464989, 8470153, 8475754], "path_names": ["Martin Havlat", "Matt Nieto", "Gabriel Bourque", "Matt Cullen", "Pierre-Marc Bouchard", "Brock Nelson"], "length": 6, "toi_percentages": [4.2, 2.1, 10.9, 2.5, 5.1], "uniqueness_score": 1.0}, {"path_ids": [8467899, 8476442, 8475268, 8466140, 8471217, 8475754], "path_names": ["Martin Havlat", "Matt Nieto", "Gabriel Bourque", "Olli Jokinen", "Andrew Ladd", "Brock Nelson"], "length": 6, "toi_percentages": [4.2, 2.1, 2.7, 6.2, 9.4], "uniqueness_score": 1.0}, {"path_ids": [8467899, 8476442, 8479393, 8480890, 8471217, 8475754], "path_names": ["Martin Havlat", "Matt Nieto", "Noah Gregor", "Jan Jenik", "Andrew Ladd", "Brock Nelson"], "length": 6, "toi_percentages": [4.2, 2.0, 0.4, 6.7, 9.4], "uniqueness_score": 0.6}, {"path_ids": [8467899, 8476442, 8478843, 8478366, 8476458, 8475754], "path_names": ["Martin Havlat", "Matt Nieto", "Denis Malgin", "Frank Vatrano", "Ryan Strome", "Brock Nelson"], "length": 6, "toi_percentages": [4.2, 1.3, 13.7, 25.3, 9.7], "uniqueness_score": 7.2}, {"path_ids": [8467899, 8476442, 8478870, 8477935, 8476409, 8475754], "path_names": ["Martin Havlat", "Matt Nieto", "Rudolfs Balcers", "Sam Bennett", "Alan Quine", "Brock Nelson"], "length": 6, "toi_percentages": [4.2, 1.1, 4.2, 0.5, 11.4], "uniqueness_score": 0.3}, {"path_ids": [8467899, 8476442, 8483570, 8481517, 8476458, 8475754], "path_names": ["Martin Havlat", "Matt Nieto", "Ben Meyers", "Brett Leason", "Ryan Strome", "Brock Nelson"], "length": 6, "toi_percentages": [4.2, 0.5, 6.9, 6.2, 9.7], "uniqueness_score": 1.6}, {"path_ids": [8467899, 8476442, 8483570, 8477527, 8474573, 8475754], "path_names": ["Martin Havlat", "Matt Nieto", "Ben Meyers", "Ross Johnston", "Josh Bailey", "Brock Nelson"], "length": 6, "toi_percentages": [4.2, 0.5, 6.2, 7.1, 28.3], "uniqueness_score": 5.5}, {"path_ids": [8467899, 8476442, 8483570, 8483630, 8476458, 8475754], "path_names": ["Martin Havlat", "Matt Nieto", "Ben Meyers", "Pavol Regenda", "Ryan Strome", "Brock Nelson"], "length": 6, "toi_percentages": [4.2, 0.5, 1.4, 21.8, 9.7], "uniqueness_score": 3.7}, {"path_ids": [8467899, 8476442, 8480822, 8478211, 8476458, 8475754], "path_names": ["Martin Havlat", "Matt Nieto", "Martin Kaut", "Dryden Hunt", "Ryan Strome", "Brock Nelson"], "length": 6, "toi_percentages": [4.2, 0.4, 6.9, 13.8, 9.7], "uniqueness_score": 3.2}, {"path_ids": [8467899, 8476442, 8482102, 8477962, 8476458, 8475754], "path_names": ["Martin Havlat", "Matt Nieto", "Vasily Ponomarev", "Brendan Lemieux", "Ryan Strome", "Brock Nelson"], "length": 6, "toi_percentages": [4.2, 0.2, 14.5, 5.8, 9.7], "uniqueness_score": 3.0}, {"path_ids": [8467899, 8476442, 8482102, 8479344, 8476458, 8475754], "path_names": ["Martin Havlat", "Matt Nieto", "Vasily Ponomarev", "Jesse Puljujarvi", "Ryan Strome", "Brock Nelson"], "length": 6, "toi_percentages": [4.2, 0.2, 4.2, 6.1, 9.7], "uniqueness_score": 0.9}, {"path_ids": [8467899, 8476442, 8478147, 8480890, 8471217, 8475754], "path_names": ["Martin Havlat", "Matt Nieto", "Bokondji Imama", "Jan Jenik", "Andrew Ladd", "Brock Nelson"], "length": 6, "toi_percentages": [4.2, 0.1, 4.3, 6.7, 9.4], "uniqueness_score": 1.0}, {"path_ids": [8467899, 8470063, 8474001, 8470289, 8471217, 8475754], "path_names": ["Martin Havlat", "Adam Burish", "TJ Galiardi", "Jim Slater", "Andrew Ladd", "Brock Nelson"], "length": 6, "toi_percentages": [2.4, 8.9, 11.9, 4.0, 9.4], "uniqueness_score": 3.5}, {"path_ids": [8467899, 8471996, 8472410, 8473504, 8474573, 8475754], "path_names": ["Martin Havlat", "Bracken Kearns", "Stephen Gionta", "Cal Clutterbuck", "Josh Bailey", "Brock Nelson"], "length": 6, "toi_percentages": [1.5, 4.3, 4.3, 4.7, 28.3], "uniqueness_score": 4.9}, {"path_ids": [8467899, 8471996, 8472410, 8473504, 8470153, 8475754], "path_names": ["Martin Havlat", "Bracken Kearns", "Stephen Gionta", "Cal Clutterbuck", "Pierre-Marc Bouchard", "Brock Nelson"], "length": 6, "toi_percentages": [1.5, 4.3, 4.3, 2.2, 5.1], "uniqueness_score": 0.0}, {"path_ids": [8467899, 8471996, 8472410, 8473504, 8476409, 8475754], "path_names": ["Martin Havlat", "Bracken Kearns", "Stephen Gionta", "Cal Clutterbuck", "Alan Quine", "Brock Nelson"], "length": 6, "toi_percentages": [1.5, 4.3, 4.3, 0.9, 11.4], "uniqueness_score": 0.5}, {"path_ids": [8467899, 8471996, 8472410, 8473504, 8476367, 8475754], "path_names": ["Martin Havlat", "Bracken Kearns", "Stephen Gionta", "Cal Clutterbuck", "John Persson", "Brock Nelson"], "length": 6, "toi_percentages": [1.5, 4.3, 4.3, 0.5, 80.2], "uniqueness_score": 14.9}, {"path_ids": [8467899, 8471996, 8472410, 8477881, 8476409, 8475754], "path_names": ["Martin Havlat", "Bracken Kearns", "Stephen Gionta", "Connor Jones", "Alan Quine", "Brock Nelson"], "length": 6, "toi_percentages": [1.5, 4.3, 0.8, 4.9, 11.4], "uniqueness_score": 0.6}, {"path_ids": [8467899, 8471996, 8472410, 8477881, 8474573, 8475754], "path_names": ["Martin Havlat", "Bracken Kearns", "Stephen Gionta", "Connor Jones", "Josh Bailey", "Brock Nelson"], "length": 6, "toi_percentages": [1.5, 4.3, 0.8, 4.9, 28.3], "uniqueness_score": 4.2}]}