{
  "2025-12-18": {
    "easy": {
      "playerA": 8477493,
      "playerB": 8478403,
      "pathLength": 3,
      "bestUniquenessScore": 0.0,
      "solutionCount": 1446
    },
    "hard": {
      "playerA": 8470667,
      "playerB": 8475692,
      "pathLength": 7,
      "bestUniquenessScore": 0.0,
      "solutionCount": 1411
    }
  },
  "2025-12-19": {
    "easy": {
      "playerA": 8474037,
      "playerB": 8475810,
      "pathLength": 4,
      "bestUniquenessScore": 0.0,
      "solutionCount": 1413
    },
    "hard": {
      "playerA": 8482110,
      "playerB": 8478449,
      "pathLength": 6,
      "bestUniquenessScore": 0.0,
      "solutionCount": 1414
    }
  },
  "2025-12-20": {
    "easy": {
      "playerA": 8476458,
      "playerB": 8476389,
      "pathLength": 3,
      "bestUniquenessScore": 0.0,
      "solutionCount": 1510
    },
    "hard": {
      "playerA": 8482146,
      "playerB": 8477493,
      "pathLength": 6,
      "bestUniquenessScore": 0.0,
      "solutionCount": 1331
    }
  },
  "2025-12-21": {
    "easy": {
      "playerA": 8469469,
      "playerB": 8476887,
      "pathLength": 3,
      "bestUniquenessScore": 0.7,
      "solutionCount": 1415
    },
    "hard": {
      "playerA": 8467338,
      "playerB": 8470638,
      "pathLength": 5,
      "bestUniquenessScore": 0.0,
      "solutionCount": 1315
    }
  },
  "2025-12-22": {
    "easy": {
      "playerA": 8478047,
      "playerB": 8476454,
      "pathLength": 4,
      "bestUniquenessScore": 0.0,
      "solutionCount": 1412
    },
    "hard": {
      "playerA": 8474037,
      "playerB": 8477404,
      "pathLength": 5,
      "bestUniquenessScore": 0.0,
      "solutionCount": 1409
    }
  },
  "2025-12-23": {
    "easy": {
      "playerA": 8448208,
      "playerB": 8475151,
      "pathLength": 3,
      "bestUniquenessScore": 0.0,
      "solutionCount": 1465
    },
    "hard": {
      "playerA": 8482665,
      "playerB": 8478483,
      "pathLength": 6,
      "bestUniquenessScore": 0.0,
      "solutionCount": 1351
    }
  },
  "2025-12-24": {
    "easy": {
      "playerA": 8471217,
      "playerB": 8478398,
      "pathLength": 3,
      "bestUniquenessScore": 0.2,
      "solutionCount": 1430
    },
    "hard": {
      "playerA": 8480064,
      "playerB": 8478439,
      "pathLength": 6,
      "bestUniquenessScore": 1.9,
      "solutionCount": 1419
    }
  },
  "2025-12-25": {
    "easy": {
      "playerA": 8474613,
      "playerB": 8478864,
      "pathLength": 4,
      "bestUniquenessScore": 0.0,
      "solutionCount": 1417
    },
    "hard": {
      "playerA": 8481028,
      "playerB": 8479314,
      "pathLength": 5,
      "bestUniquenessScore": 1.0,
      "solutionCount": 1428
    }
  },
  "2025-12-26": {
    "easy": {
      "playerA": 8476456,
      "playerB": 8479314,
      "pathLength": 4,
      "bestUniquenessScore": 0.0,
      "solutionCount": 1477
    },
    "hard": {
      "playerA": 8458529,
      "playerB": 8476399,
      "pathLength": 7,
      "bestUniquenessScore": 1.2,
      "solutionCount": 1416
    }
  },
  "2025-12-27": {
    "easy": {
      "playerA": 8480801,
      "playerB": 8474161,
      "pathLength": 4,
      "bestUniquenessScore": 2.6,
      "solutionCount": 1428
    },
    "hard": {
      "playerA": 8482667,
      "playerB": 8466138,
      "pathLength": 5,
      "bestUniquenessScore": 0.0,
      "solutionCount": 1450
    }
  },
  "2025-12-28": {
    "easy": {
      "playerA": 8477934,
      "playerB": 8478445,
      "pathLength": 4,
      "bestUniquenessScore": 0.0,
      "solutionCount": 1414
    },
    "hard": {
      "playerA": 8471676,
      "playerB": 8470041,
      "pathLength": 5,
      "bestUniquenessScore": 0.0,
      "solutionCount": 1427
    }
  },
  "2025-12-29": {
    "easy": {
      "playerA": 8467338,
      "playerB": 8478498,
      "pathLength": 4,
      "bestUniquenessScore": 0.0,
      "solutionCount": 1303
    },
    "hard": {
      "playerA": 8478402,
      "playerB": 8475314,
      "pathLength": 5,
      "bestUniquenessScore": 0.0,
      "solutionCount": 1417
    }
  },
  "2025-12-30": {
    "easy": {
      "playerA": 8459492,
      "playerB": 8480113,
      "pathLength": 4,
      "bestUniquenessScore": 1.8,
      "solutionCount": 1311
    },
    "hard": {
      "playerA": 8474613,
      "playerB": 8471214,
      "pathLength": 9,
      "bestUniquenessScore": 0.0,
      "solutionCount": 1405
    }
  },
  "2025-12-31": {
    "easy": {
      "playerA": 8476479,
      "playerB": 8475793,
      "pathLength": 4,
      "bestUniquenessScore": 0.0,
      "solutionCount": 1432
    },
    "hard": {
      "playerA": 8460542,
      "playerB": 8475786,
      "pathLength": 9,
      "bestUniquenessScore": 0.0,
      "solutionCount": 1305
    }
  },
  "2026-01-01": {
    "easy": {
      "playerA": 8477955,
      "playerB": 8475314,
      "pathLength": 4,
      "bestUniquenessScore": 0.0,
      "solutionCount": 1423
    },
    "hard": {
      "playerA": 8480023,
      "playerB": 8481557,
      "pathLength": 9,
      "bestUniquenessScore": 0.5,
      "solutionCount": 1218
    }
  },
  "2026-01-02": {
    "easy": {
      "playerA": 8470655,
      "playerB": 8475744,
      "pathLength": 3,
      "bestUniquenessScore": 0.0,
      "solutionCount": 1430
    },
    "hard": {
      "playerA": 8481656,
      "playerB": 8466148,
      "pathLength": 5,
      "bestUniquenessScore": 0.0,
      "solutionCount": 1304
    }
  },
  "2026-01-03": {
    "easy": {
      "playerA": 8462077,
      "playerB": 8475168,
      "pathLength": 3,
      "bestUniquenessScore": 0.0,
      "solutionCount": 1419
    },
    "hard": {
      "playerA": 8483445,
      "playerB": 8474870,
      "pathLength": 5,
      "bestUniquenessScore": 6.3,
      "solutionCount": 1424
    }
  },
  "2026-01-04": {
    "easy": {
      "playerA": 8482110,
      "playerB": 8466139,
      "pathLength": 4,
      "bestUniquenessScore": 0.0,
      "solutionCount": 1431
    },
    "hard": {
      "playerA": 8457981,
      "playerB": 8477940,
      "pathLength": 6,
      "bestUniquenessScore": 1.2,
      "solutionCount": 1372
    }
  },
  "2026-01-05": {
    "easy": {
      "playerA": 8470596,
      "playerB": 8477956,
      "pathLength": 3,
      "bestUniquenessScore": 0.0,
      "solutionCount": 1435
    },
    "hard": {
      "playerA": 8467899,
      "playerB": 8477934,
      "pathLength": 10,
      "bestUniquenessScore": 0.1,
      "solutionCount": 1347
    }
  },
  "2026-01-06": {
    "easy": {
      "playerA": 8470667,
      "playerB": 8475184,
      "pathLength": 4,
      "bestUniquenessScore": 0.0,
      "solutionCount": 1430
    },
    "hard": {
      "playerA": 8476438,
      "playerB": 8473563,
      "pathLength": 7,
      "bestUniquenessScore": 0.0,
      "solutionCount": 1406
    }
  },
  "2026-01-07": {
    "easy": {
      "playerA": 8470153,
      "playerB": 8475169,
      "pathLength": 4,
      "bestUniquenessScore": 0.4,
      "solutionCount": 1429
    },
    "hard": {
      "playerA": 8478047,
      "playerB": 8475754,
      "pathLength": 8,
      "bestUniquenessScore": 0.2,
      "solutionCount": 1426
    }
  },
  "2026-01-08": {
    "easy": {
      "playerA": 8482222,
      "playerB": 8470794,
      "pathLength": 4,
      "bestUniquenessScore": 0.0,
      "solutionCount": 1506
    },
    "hard": {
      "playerA": 8458590,
      "playerB": 8473579,
      "pathLength": 8,
      "bestUniquenessScore": 0.7,
      "solutionCount": 1226
    }
  },
  "2026-01-09": {
    "easy": {
      "playerA": 8482149,
      "playerB": 8473412,
      "pathLength": 4,
      "bestUniquenessScore": 1.0,
      "solutionCount": 1445
    },
    "hard": {
      "playerA": 8467988,
      "playerB": 8478864,
      "pathLength": 6,
      "bestUniquenessScore": 0.9,
      "solutionCount": 1240
    }
  },
  "2026-01-10": {
    "easy": {
      "playerA": 8468486,
      "playerB": 8478439,
      "pathLength": 4,
      "bestUniquenessScore": 0.0,
      "solutionCount": 1456
    },
    "hard": {
      "playerA": 8470162,
      "playerB": 8477409,
      "pathLength": 5,
      "bestUniquenessScore": 0.3,
      "solutionCount": 1411
    }
  },
  "2026-01-11": {
    "easy": {
      "playerA": 8482079,
      "playerB": 8471214,
      "pathLength": 4,
      "bestUniquenessScore": 0.1,
      "solutionCount": 1426
    },
    "hard": {
      "playerA": 8478403,
      "playerB": 8477496,
      "pathLength": 6,
      "bestUniquenessScore": 0.3,
      "solutionCount": 1420
    }
  },
  "2026-01-12": {
    "easy": {
      "playerA": 8458529,
      "playerB": 8477933,
      "pathLength": 4,
      "bestUniquenessScore": 0.7,
      "solutionCount": 1408
    },
    "hard": {
      "playerA": 8459492,
      "playerB": 8482079,
      "pathLength": 6,
      "bestUniquenessScore": 0.1,
      "solutionCount": 1247
    }
  },
  "2026-01-13": {
    "easy": {
      "playerA": 8484145,
      "playerB": 8475166,
      "pathLength": 4,
      "bestUniquenessScore": 0.8,
      "solutionCount": 1373
    },
    "hard": {
      "playerA": 8482740,
      "playerB": 8474150,
      "pathLength": 6,
      "bestUniquenessScore": 0.0,
      "solutionCount": 1325
    }
  },
  "2026-01-14": {
    "easy": {
      "playerA": 8482665,
      "playerB": 8478402,
      "pathLength": 4,
      "bestUniquenessScore": 0.0,
      "solutionCount": 1419
    },
    "hard": {
      "playerA": 8479339,
      "playerB": 8471217,
      "pathLength": 5,
      "bestUniquenessScore": 1.2,
      "solutionCount": 1429
    }
  },
  "2026-01-15": {
    "easy": {
      "playerA": 8460621,
      "playerB": 8476905,
      "pathLength": 4,
      "bestUniquenessScore": 0.0,
      "solutionCount": 1360
    },
    "hard": {
      "playerA": 8480027,
      "playerB": 8476881,
      "pathLength": 6,
      "bestUniquenessScore": 0.0,
      "solutionCount": 1429
    }
  },
  "2026-01-16": {
    "easy": {
      "playerA": 8481533,
      "playerB": 8478550,
      "pathLength": 3,
      "bestUniquenessScore": 1.9,
      "solutionCount": 1428
    },
    "hard": {
      "playerA": 8484153,
      "playerB": 8476389,
      "pathLength": 5,
      "bestUniquenessScore": 1.4,
      "solutionCount": 1423
    }
  },
  "2026-01-17": {
    "easy": {
      "playerA": 8475098,
      "playerB": 8471215,
      "pathLength": 3,
      "bestUniquenessScore": 0.3,
      "solutionCount": 1420
    },
    "hard": {
      "playerA": 8482074,
      "playerB": 8477497,
      "pathLength": 6,
      "bestUniquenessScore": 0.8,
      "solutionCount": 1442
    }
  },
  "2026-01-18": {
    "easy": {
      "playerA": 8470162,
      "playerB": 8476399,
      "pathLength": 4,
      "bestUniquenessScore": 0.1,
      "solutionCount": 1427
    },
    "hard": {
      "playerA": 8479385,
      "playerB": 8471698,
      "pathLength": 13,
      "bestUniquenessScore": 0.0,
      "solutionCount": 1423
    }
  },
  "2026-01-19": {
    "easy": {
      "playerA": 8481557,
      "playerB": 8473563,
      "pathLength": 4,
      "bestUniquenessScore": 2.7,
      "solutionCount": 1425
    },
    "hard": {
      "playerA": 8474586,
      "playerB": 8479318,
      "pathLength": 5,
      "bestUniquenessScore": 0.0,
      "solutionCount": 1412
    }
  },
  "2026-01-20": {
    "easy": {
      "playerA": 8466138,
      "playerB": 8480027,
      "pathLength": 3,
      "bestUniquenessScore": 1.4,
      "solutionCount": 1424
    },
    "hard": {
      "playerA": 8482109,
      "playerB": 8473544,
      "pathLength": 7,
      "bestUniquenessScore": 0.0,
      "solutionCount": 1430
    }
  },
  "2026-01-21": {
    "easy": {
      "playerA": 8484144,
      "playerB": 8482078,
      "pathLength": 4,
      "bestUniquenessScore": 1.4,
      "solutionCount": 1420
    },
    "hard": {
      "playerA": 8448208,
      "playerB": 8477939,
      "pathLength": 7,
      "bestUniquenessScore": 0.0,
      "solutionCount": 1355
    }
  },
  "2026-01-22": {
    "easy": {
      "playerA": 8468434,
      "playerB": 8475170,
      "pathLength": 4,
      "bestUniquenessScore": 1.5,
      "solutionCount": 1447
    },
    "hard": {
      "playerA": 8469544,
      "playerB": 8475744,
      "pathLength": 6,
      "bestUniquenessScore": 0.0,
      "solutionCount": 1311
    }
  },
  "2026-01-23": {
    "easy": {
      "playerA": 8467353,
      "playerB": 8471682,
      "pathLength": 4,
      "bestUniquenessScore": 0.0,
      "solutionCount": 1451
    },
    "hard": {
      "playerA": 8475151,
      "playerB": 8476454,
      "pathLength": 6,
      "bestUniquenessScore": 0.0,
      "solutionCount": 1430
    }
  },
  "2026-01-24": {
    "easy": {
      "playerA": 8479337,
      "playerB": 8466148,
      "pathLength": 4,
      "bestUniquenessScore": 0.0,
      "solutionCount": 1474
    },
    "hard": {
      "playerA": 8466378,
      "playerB": 8479542,
      "pathLength": 5,
      "bestUniquenessScore": 0.0,
      "solutionCount": 1438
    }
  }
}