{
  "2025-08-16": {
    "playerA": 8478420,
    "playerB": 8448208
  },
  "2025-08-17": {
    "playerA": 8477492,
    "playerB": 8471685
  },
  "2025-08-18": {
    "playerA": 8474141,
    "playerB": 8480801
  },
  "2025-08-19": {
    "playerA": 8479407,
    "playerB": 8477956
  },
  "2025-08-20": {
    "playerA": 8475166,
    "playerB": 8479343
  },
  "2025-08-21": {
    "playerA": 8471214,
    "playerB": 8478403
  },
  "2025-08-22": {
    "playerA": 8471214,
    "playerB": 8480801
  },
  "2025-08-23": {
    "playerA": 8478550,
    "playerB": 8475166
  },
  "2025-08-24": {
    "playerA": 8471675,
    "playerB": 8477946
  },
  "2025-08-25": {
    "playerA": 8467329,
    "playerB": 8473994
  },
  "2025-08-26": {
    "playerA": 8477493,
    "playerB": 8471214
  },
  "2025-08-27": {
    "playerA": 8478550,
    "playerB": 8475784
  },
  "2025-08-28": {
    "playerA": 8477493,
    "playerB": 8478550
  },
  "2025-08-29": {
    "playerA": 8480027,
    "playerB": 8479314
  },
  "2025-08-30": {
    "playerA": 8476453,
    "playerB": 8481559
  },
  "2025-08-31": {
    "playerA": 8470595,
    "playerB": 8473548
  },
  "2025-09-01": {
    "playerA": 8479407,
    "playerB": 8478550
  },
  "2025-09-02": {
    "playerA": 8473604,
    "playerB": 8471215
  },
  "2025-09-03": {
    "playerA": 8479343,
    "playerB": 8482078
  },
  "2025-09-04": {
    "playerA": 8470595,
    "playerB": 8473548
  },
  "2025-09-05": {
    "playerA": 8482078,
    "playerB": 8481559
  },
  "2025-09-06": {
    "playerA": 8467329,
    "playerB": 8473994
  },
  "2025-09-07": {
    "playerA": 8477946,
    "playerB": 8475166
  },
  "2025-09-08": {
    "playerA": 8480018,
    "playerB": 8477493
  },
  "2025-09-09": {
    "playerA": 8478403,
    "playerB": 8473604
  },
  "2025-09-10": {
    "playerA": 8474564,
    "playerB": 8477956
  },
  "2025-09-11": {
    "playerA": 8478864,
    "playerB": 8478427
  },
  "2025-09-12": {
    "playerA": 8480018,
    "playerB": 8476346
  },
  "2025-09-13": {
    "playerA": 8476456,
    "playerB": 8471214
  },
  "2025-09-14": {
    "playerA": 8476453,
    "playerB": 8479407
  },
  "2025-09-15": {
    "playerA": 8480018,
    "playerB": 8476346
  },
  "2025-09-16": {
    "playerA": 8466378,
    "playerB": 8474141
  },
  "2025-09-17": {
    "playerA": 8462042,
    "playerB": 8471214
  },
  "2025-09-18": {
    "playerA": 8479407,
    "playerB": 8478420
  },
  "2025-09-19": {
    "playerA": 8480018,
    "playerB": 8475784
  },
  "2025-09-20": {
    "playerA": 8477934,
    "playerB": 8481559
  },
  "2025-09-21": {
    "playerA": 8471685,
    "playerB": 8479407
  },
  "2025-09-22": {
    "playerA": 8478439,
    "playerB": 8476346
  },
  "2025-09-23": {
    "playerA": 8480018,
    "playerB": 8475784
  },
  "2025-09-24": {
    "playerA": 8478439,
    "playerB": 8480801
  },
  "2025-09-25": {
    "playerA": 8466378,
    "playerB": 8473548
  },
  "2025-09-26": {
    "playerA": 8477934,
    "playerB": 8479407
  },
  "2025-09-27": {
    "playerA": 8480018,
    "playerB": 8477946
  },
  "2025-09-28": {
    "playerA": 8477933,
    "playerB": 8448208
  },
  "2025-09-29": {
    "playerA": 8479318,
    "playerB": 8471214
  },
  "2025-09-30": {
    "playerA": 8471215,
    "playerB": 8448208
  },
  "2025-10-01": {
    "playerA": 8475784,
    "playerB": 8478550
  },
  "2025-10-02": {
    "playerA": 8477946,
    "playerB": 8473512
  },
  "2025-10-03": {
    "playerA": 8474141,
    "playerB": 8476453
  },
  "2025-10-04": {
    "playerA": 8477946,
    "playerB": 8479407
  },
  "2025-10-05": {
    "playerA": 8471215,
    "playerB": 8479420
  },
  "2025-10-06": {
    "playerA": 8477493,
    "playerB": 8474141
  },
  "2025-10-07": {
    "playerA": 8479337,
    "playerB": 8476456
  },
  "2025-10-08": {
    "playerA": 8479407,
    "playerB": 8470612
  },
  "2025-10-09": {
    "playerA": 8474141,
    "playerB": 8471215
  },
  "2025-10-10": {
    "playerA": 8479314,
    "playerB": 8479407
  },
  "2025-10-11": {
    "playerA": 8480018,
    "playerB": 8477956
  },
  "2025-10-12": {
    "playerA": 8479318,
    "playerB": 8473994
  },
  "2025-10-13": {
    "playerA": 8482078,
    "playerB": 8481559
  },
  "2025-10-14": {
    "playerA": 8471215,
    "playerB": 8482078
  }
}